{
  "type": "File",
  "start": 0,
  "end": 663,
  "loc": {
    "start": {
      "line": 1,
      "column": 0
    },
    "end": {
      "line": 22,
      "column": 0
    }
  },
  "program": {
    "type": "Program",
    "start": 0,
    "end": 663,
    "loc": {
      "start": {
        "line": 1,
        "column": 0
      },
      "end": {
        "line": 22,
        "column": 0
      }
    },
    "sourceType": "module",
    "body": [
      {
        "type": "ExportNamedDeclaration",
        "start": 0,
        "end": 28,
        "loc": {
          "start": {
            "line": 1,
            "column": 0
          },
          "end": {
            "line": 1,
            "column": 28
          }
        },
        "specifiers": [
          {
            "type": "ExportDefaultSpecifier",
            "start": 7,
            "end": 12,
            "loc": {
              "start": {
                "line": 1,
                "column": 7
              },
              "end": {
                "line": 1,
                "column": 12
              }
            },
            "exported": {
              "type": "Identifier",
              "start": 7,
              "end": 12,
              "loc": {
                "start": {
                  "line": 1,
                  "column": 7
                },
                "end": {
                  "line": 1,
                  "column": 12
                },
                "identifierName": "comp1"
              },
              "name": "comp1"
            }
          }
        ],
        "source": {
          "type": "StringLiteral",
          "start": 18,
          "end": 27,
          "loc": {
            "start": {
              "line": 1,
              "column": 18
            },
            "end": {
              "line": 1,
              "column": 27
            }
          },
          "extra": {
            "rawValue": "./comp1",
            "raw": "'./comp1'"
          },
          "value": "./comp1"
        }
      },
      {
        "type": "ExportNamedDeclaration",
        "start": 29,
        "end": 57,
        "loc": {
          "start": {
            "line": 2,
            "column": 0
          },
          "end": {
            "line": 2,
            "column": 28
          }
        },
        "specifiers": [
          {
            "type": "ExportDefaultSpecifier",
            "start": 36,
            "end": 41,
            "loc": {
              "start": {
                "line": 2,
                "column": 7
              },
              "end": {
                "line": 2,
                "column": 12
              }
            },
            "exported": {
              "type": "Identifier",
              "start": 36,
              "end": 41,
              "loc": {
                "start": {
                  "line": 2,
                  "column": 7
                },
                "end": {
                  "line": 2,
                  "column": 12
                },
                "identifierName": "comp2"
              },
              "name": "comp2"
            }
          }
        ],
        "source": {
          "type": "StringLiteral",
          "start": 47,
          "end": 56,
          "loc": {
            "start": {
              "line": 2,
              "column": 18
            },
            "end": {
              "line": 2,
              "column": 27
            }
          },
          "extra": {
            "rawValue": "./comp2",
            "raw": "'./comp2'"
          },
          "value": "./comp2"
        }
      },
      {
        "type": "ExportNamedDeclaration",
        "start": 58,
        "end": 116,
        "loc": {
          "start": {
            "line": 3,
            "column": 0
          },
          "end": {
            "line": 3,
            "column": 58
          }
        },
        "declaration": null,
        "specifiers": [
          {
            "type": "ExportSpecifier",
            "start": 67,
            "end": 78,
            "loc": {
              "start": {
                "line": 3,
                "column": 9
              },
              "end": {
                "line": 3,
                "column": 20
              }
            },
            "local": {
              "type": "Identifier",
              "start": 67,
              "end": 78,
              "loc": {
                "start": {
                  "line": 3,
                  "column": 9
                },
                "end": {
                  "line": 3,
                  "column": 20
                },
                "identifierName": "multiSelect"
              },
              "name": "multiSelect"
            },
            "exported": {
              "type": "Identifier",
              "start": 67,
              "end": 78,
              "loc": {
                "start": {
                  "line": 3,
                  "column": 9
                },
                "end": {
                  "line": 3,
                  "column": 20
                },
                "identifierName": "multiSelect"
              },
              "name": "multiSelect"
            }
          },
          {
            "type": "ExportSpecifier",
            "start": 80,
            "end": 98,
            "loc": {
              "start": {
                "line": 3,
                "column": 22
              },
              "end": {
                "line": 3,
                "column": 40
              }
            },
            "local": {
              "type": "Identifier",
              "start": 80,
              "end": 98,
              "loc": {
                "start": {
                  "line": 3,
                  "column": 22
                },
                "end": {
                  "line": 3,
                  "column": 40
                },
                "identifierName": "multiSelectOptions"
              },
              "name": "multiSelectOptions"
            },
            "exported": {
              "type": "Identifier",
              "start": 80,
              "end": 98,
              "loc": {
                "start": {
                  "line": 3,
                  "column": 22
                },
                "end": {
                  "line": 3,
                  "column": 40
                },
                "identifierName": "multiSelectOptions"
              },
              "name": "multiSelectOptions"
            }
          }
        ],
        "source": {
          "type": "StringLiteral",
          "start": 106,
          "end": 115,
          "loc": {
            "start": {
              "line": 3,
              "column": 48
            },
            "end": {
              "line": 3,
              "column": 57
            }
          },
          "extra": {
            "rawValue": "./comp3",
            "raw": "'./comp3'"
          },
          "value": "./comp3"
        }
      },
      {
        "type": "ExportNamedDeclaration",
        "start": 117,
        "end": 145,
        "loc": {
          "start": {
            "line": 4,
            "column": 0
          },
          "end": {
            "line": 4,
            "column": 28
          }
        },
        "specifiers": [
          {
            "type": "ExportDefaultSpecifier",
            "start": 124,
            "end": 129,
            "loc": {
              "start": {
                "line": 4,
                "column": 7
              },
              "end": {
                "line": 4,
                "column": 12
              }
            },
            "exported": {
              "type": "Identifier",
              "start": 124,
              "end": 129,
              "loc": {
                "start": {
                  "line": 4,
                  "column": 7
                },
                "end": {
                  "line": 4,
                  "column": 12
                },
                "identifierName": "comp4"
              },
              "name": "comp4"
            }
          }
        ],
        "source": {
          "type": "StringLiteral",
          "start": 135,
          "end": 144,
          "loc": {
            "start": {
              "line": 4,
              "column": 18
            },
            "end": {
              "line": 4,
              "column": 27
            }
          },
          "extra": {
            "rawValue": "./comp4",
            "raw": "'./comp4'"
          },
          "value": "./comp4"
        }
      },
      {
        "type": "ExportNamedDeclaration",
        "start": 146,
        "end": 174,
        "loc": {
          "start": {
            "line": 5,
            "column": 0
          },
          "end": {
            "line": 5,
            "column": 28
          }
        },
        "specifiers": [
          {
            "type": "ExportDefaultSpecifier",
            "start": 153,
            "end": 158,
            "loc": {
              "start": {
                "line": 5,
                "column": 7
              },
              "end": {
                "line": 5,
                "column": 12
              }
            },
            "exported": {
              "type": "Identifier",
              "start": 153,
              "end": 158,
              "loc": {
                "start": {
                  "line": 5,
                  "column": 7
                },
                "end": {
                  "line": 5,
                  "column": 12
                },
                "identifierName": "comp5"
              },
              "name": "comp5"
            }
          }
        ],
        "source": {
          "type": "StringLiteral",
          "start": 164,
          "end": 173,
          "loc": {
            "start": {
              "line": 5,
              "column": 18
            },
            "end": {
              "line": 5,
              "column": 27
            }
          },
          "extra": {
            "rawValue": "./comp5",
            "raw": "'./comp5'"
          },
          "value": "./comp5"
        }
      },
      {
        "type": "ExportNamedDeclaration",
        "start": 175,
        "end": 203,
        "loc": {
          "start": {
            "line": 6,
            "column": 0
          },
          "end": {
            "line": 6,
            "column": 28
          }
        },
        "specifiers": [
          {
            "type": "ExportDefaultSpecifier",
            "start": 182,
            "end": 187,
            "loc": {
              "start": {
                "line": 6,
                "column": 7
              },
              "end": {
                "line": 6,
                "column": 12
              }
            },
            "exported": {
              "type": "Identifier",
              "start": 182,
              "end": 187,
              "loc": {
                "start": {
                  "line": 6,
                  "column": 7
                },
                "end": {
                  "line": 6,
                  "column": 12
                },
                "identifierName": "comp6"
              },
              "name": "comp6"
            }
          }
        ],
        "source": {
          "type": "StringLiteral",
          "start": 193,
          "end": 202,
          "loc": {
            "start": {
              "line": 6,
              "column": 18
            },
            "end": {
              "line": 6,
              "column": 27
            }
          },
          "extra": {
            "rawValue": "./comp6",
            "raw": "'./comp6'"
          },
          "value": "./comp6"
        }
      },
      {
        "type": "ExportNamedDeclaration",
        "start": 204,
        "end": 232,
        "loc": {
          "start": {
            "line": 7,
            "column": 0
          },
          "end": {
            "line": 7,
            "column": 28
          }
        },
        "specifiers": [
          {
            "type": "ExportDefaultSpecifier",
            "start": 211,
            "end": 216,
            "loc": {
              "start": {
                "line": 7,
                "column": 7
              },
              "end": {
                "line": 7,
                "column": 12
              }
            },
            "exported": {
              "type": "Identifier",
              "start": 211,
              "end": 216,
              "loc": {
                "start": {
                  "line": 7,
                  "column": 7
                },
                "end": {
                  "line": 7,
                  "column": 12
                },
                "identifierName": "comp7"
              },
              "name": "comp7"
            }
          }
        ],
        "source": {
          "type": "StringLiteral",
          "start": 222,
          "end": 231,
          "loc": {
            "start": {
              "line": 7,
              "column": 18
            },
            "end": {
              "line": 7,
              "column": 27
            }
          },
          "extra": {
            "rawValue": "./comp7",
            "raw": "'./comp7'"
          },
          "value": "./comp7"
        }
      },
      {
        "type": "ExportNamedDeclaration",
        "start": 233,
        "end": 261,
        "loc": {
          "start": {
            "line": 8,
            "column": 0
          },
          "end": {
            "line": 8,
            "column": 28
          }
        },
        "specifiers": [
          {
            "type": "ExportDefaultSpecifier",
            "start": 240,
            "end": 245,
            "loc": {
              "start": {
                "line": 8,
                "column": 7
              },
              "end": {
                "line": 8,
                "column": 12
              }
            },
            "exported": {
              "type": "Identifier",
              "start": 240,
              "end": 245,
              "loc": {
                "start": {
                  "line": 8,
                  "column": 7
                },
                "end": {
                  "line": 8,
                  "column": 12
                },
                "identifierName": "comp8"
              },
              "name": "comp8"
            }
          }
        ],
        "source": {
          "type": "StringLiteral",
          "start": 251,
          "end": 260,
          "loc": {
            "start": {
              "line": 8,
              "column": 18
            },
            "end": {
              "line": 8,
              "column": 27
            }
          },
          "extra": {
            "rawValue": "./comp8",
            "raw": "'./comp8'"
          },
          "value": "./comp8"
        }
      },
      {
        "type": "ExportNamedDeclaration",
        "start": 262,
        "end": 290,
        "loc": {
          "start": {
            "line": 9,
            "column": 0
          },
          "end": {
            "line": 9,
            "column": 28
          }
        },
        "specifiers": [
          {
            "type": "ExportDefaultSpecifier",
            "start": 269,
            "end": 274,
            "loc": {
              "start": {
                "line": 9,
                "column": 7
              },
              "end": {
                "line": 9,
                "column": 12
              }
            },
            "exported": {
              "type": "Identifier",
              "start": 269,
              "end": 274,
              "loc": {
                "start": {
                  "line": 9,
                  "column": 7
                },
                "end": {
                  "line": 9,
                  "column": 12
                },
                "identifierName": "comp9"
              },
              "name": "comp9"
            }
          }
        ],
        "source": {
          "type": "StringLiteral",
          "start": 280,
          "end": 289,
          "loc": {
            "start": {
              "line": 9,
              "column": 18
            },
            "end": {
              "line": 9,
              "column": 27
            }
          },
          "extra": {
            "rawValue": "./comp9",
            "raw": "'./comp9'"
          },
          "value": "./comp9"
        }
      },
      {
        "type": "ExportNamedDeclaration",
        "start": 291,
        "end": 321,
        "loc": {
          "start": {
            "line": 10,
            "column": 0
          },
          "end": {
            "line": 10,
            "column": 30
          }
        },
        "specifiers": [
          {
            "type": "ExportDefaultSpecifier",
            "start": 298,
            "end": 304,
            "loc": {
              "start": {
                "line": 10,
                "column": 7
              },
              "end": {
                "line": 10,
                "column": 13
              }
            },
            "exported": {
              "type": "Identifier",
              "start": 298,
              "end": 304,
              "loc": {
                "start": {
                  "line": 10,
                  "column": 7
                },
                "end": {
                  "line": 10,
                  "column": 13
                },
                "identifierName": "comp10"
              },
              "name": "comp10"
            }
          }
        ],
        "source": {
          "type": "StringLiteral",
          "start": 310,
          "end": 320,
          "loc": {
            "start": {
              "line": 10,
              "column": 19
            },
            "end": {
              "line": 10,
              "column": 29
            }
          },
          "extra": {
            "rawValue": "./comp10",
            "raw": "'./comp10'"
          },
          "value": "./comp10"
        }
      },
      {
        "type": "ExportNamedDeclaration",
        "start": 322,
        "end": 352,
        "loc": {
          "start": {
            "line": 11,
            "column": 0
          },
          "end": {
            "line": 11,
            "column": 30
          }
        },
        "specifiers": [
          {
            "type": "ExportDefaultSpecifier",
            "start": 329,
            "end": 335,
            "loc": {
              "start": {
                "line": 11,
                "column": 7
              },
              "end": {
                "line": 11,
                "column": 13
              }
            },
            "exported": {
              "type": "Identifier",
              "start": 329,
              "end": 335,
              "loc": {
                "start": {
                  "line": 11,
                  "column": 7
                },
                "end": {
                  "line": 11,
                  "column": 13
                },
                "identifierName": "comp11"
              },
              "name": "comp11"
            }
          }
        ],
        "source": {
          "type": "StringLiteral",
          "start": 341,
          "end": 351,
          "loc": {
            "start": {
              "line": 11,
              "column": 19
            },
            "end": {
              "line": 11,
              "column": 29
            }
          },
          "extra": {
            "rawValue": "./comp11",
            "raw": "'./comp11'"
          },
          "value": "./comp11"
        }
      },
      {
        "type": "ExportNamedDeclaration",
        "start": 353,
        "end": 383,
        "loc": {
          "start": {
            "line": 12,
            "column": 0
          },
          "end": {
            "line": 12,
            "column": 30
          }
        },
        "specifiers": [
          {
            "type": "ExportDefaultSpecifier",
            "start": 360,
            "end": 366,
            "loc": {
              "start": {
                "line": 12,
                "column": 7
              },
              "end": {
                "line": 12,
                "column": 13
              }
            },
            "exported": {
              "type": "Identifier",
              "start": 360,
              "end": 366,
              "loc": {
                "start": {
                  "line": 12,
                  "column": 7
                },
                "end": {
                  "line": 12,
                  "column": 13
                },
                "identifierName": "comp12"
              },
              "name": "comp12"
            }
          }
        ],
        "source": {
          "type": "StringLiteral",
          "start": 372,
          "end": 382,
          "loc": {
            "start": {
              "line": 12,
              "column": 19
            },
            "end": {
              "line": 12,
              "column": 29
            }
          },
          "extra": {
            "rawValue": "./comp12",
            "raw": "'./comp12'"
          },
          "value": "./comp12"
        }
      },
      {
        "type": "ExportNamedDeclaration",
        "start": 384,
        "end": 414,
        "loc": {
          "start": {
            "line": 13,
            "column": 0
          },
          "end": {
            "line": 13,
            "column": 30
          }
        },
        "specifiers": [
          {
            "type": "ExportDefaultSpecifier",
            "start": 391,
            "end": 397,
            "loc": {
              "start": {
                "line": 13,
                "column": 7
              },
              "end": {
                "line": 13,
                "column": 13
              }
            },
            "exported": {
              "type": "Identifier",
              "start": 391,
              "end": 397,
              "loc": {
                "start": {
                  "line": 13,
                  "column": 7
                },
                "end": {
                  "line": 13,
                  "column": 13
                },
                "identifierName": "comp13"
              },
              "name": "comp13"
            }
          }
        ],
        "source": {
          "type": "StringLiteral",
          "start": 403,
          "end": 413,
          "loc": {
            "start": {
              "line": 13,
              "column": 19
            },
            "end": {
              "line": 13,
              "column": 29
            }
          },
          "extra": {
            "rawValue": "./comp13",
            "raw": "'./comp13'"
          },
          "value": "./comp13"
        }
      },
      {
        "type": "ExportNamedDeclaration",
        "start": 415,
        "end": 445,
        "loc": {
          "start": {
            "line": 14,
            "column": 0
          },
          "end": {
            "line": 14,
            "column": 30
          }
        },
        "specifiers": [
          {
            "type": "ExportDefaultSpecifier",
            "start": 422,
            "end": 428,
            "loc": {
              "start": {
                "line": 14,
                "column": 7
              },
              "end": {
                "line": 14,
                "column": 13
              }
            },
            "exported": {
              "type": "Identifier",
              "start": 422,
              "end": 428,
              "loc": {
                "start": {
                  "line": 14,
                  "column": 7
                },
                "end": {
                  "line": 14,
                  "column": 13
                },
                "identifierName": "comp14"
              },
              "name": "comp14"
            }
          }
        ],
        "source": {
          "type": "StringLiteral",
          "start": 434,
          "end": 444,
          "loc": {
            "start": {
              "line": 14,
              "column": 19
            },
            "end": {
              "line": 14,
              "column": 29
            }
          },
          "extra": {
            "rawValue": "./comp14",
            "raw": "'./comp14'"
          },
          "value": "./comp14"
        }
      },
      {
        "type": "ExportNamedDeclaration",
        "start": 446,
        "end": 476,
        "loc": {
          "start": {
            "line": 15,
            "column": 0
          },
          "end": {
            "line": 15,
            "column": 30
          }
        },
        "specifiers": [
          {
            "type": "ExportDefaultSpecifier",
            "start": 453,
            "end": 459,
            "loc": {
              "start": {
                "line": 15,
                "column": 7
              },
              "end": {
                "line": 15,
                "column": 13
              }
            },
            "exported": {
              "type": "Identifier",
              "start": 453,
              "end": 459,
              "loc": {
                "start": {
                  "line": 15,
                  "column": 7
                },
                "end": {
                  "line": 15,
                  "column": 13
                },
                "identifierName": "comp15"
              },
              "name": "comp15"
            }
          }
        ],
        "source": {
          "type": "StringLiteral",
          "start": 465,
          "end": 475,
          "loc": {
            "start": {
              "line": 15,
              "column": 19
            },
            "end": {
              "line": 15,
              "column": 29
            }
          },
          "extra": {
            "rawValue": "./comp15",
            "raw": "'./comp15'"
          },
          "value": "./comp15"
        }
      },
      {
        "type": "ExportNamedDeclaration",
        "start": 477,
        "end": 507,
        "loc": {
          "start": {
            "line": 16,
            "column": 0
          },
          "end": {
            "line": 16,
            "column": 30
          }
        },
        "specifiers": [
          {
            "type": "ExportDefaultSpecifier",
            "start": 484,
            "end": 490,
            "loc": {
              "start": {
                "line": 16,
                "column": 7
              },
              "end": {
                "line": 16,
                "column": 13
              }
            },
            "exported": {
              "type": "Identifier",
              "start": 484,
              "end": 490,
              "loc": {
                "start": {
                  "line": 16,
                  "column": 7
                },
                "end": {
                  "line": 16,
                  "column": 13
                },
                "identifierName": "comp16"
              },
              "name": "comp16"
            }
          }
        ],
        "source": {
          "type": "StringLiteral",
          "start": 496,
          "end": 506,
          "loc": {
            "start": {
              "line": 16,
              "column": 19
            },
            "end": {
              "line": 16,
              "column": 29
            }
          },
          "extra": {
            "rawValue": "./comp16",
            "raw": "'./comp16'"
          },
          "value": "./comp16"
        }
      },
      {
        "type": "ExportNamedDeclaration",
        "start": 508,
        "end": 538,
        "loc": {
          "start": {
            "line": 17,
            "column": 0
          },
          "end": {
            "line": 17,
            "column": 30
          }
        },
        "specifiers": [
          {
            "type": "ExportDefaultSpecifier",
            "start": 515,
            "end": 521,
            "loc": {
              "start": {
                "line": 17,
                "column": 7
              },
              "end": {
                "line": 17,
                "column": 13
              }
            },
            "exported": {
              "type": "Identifier",
              "start": 515,
              "end": 521,
              "loc": {
                "start": {
                  "line": 17,
                  "column": 7
                },
                "end": {
                  "line": 17,
                  "column": 13
                },
                "identifierName": "comp17"
              },
              "name": "comp17"
            }
          }
        ],
        "source": {
          "type": "StringLiteral",
          "start": 527,
          "end": 537,
          "loc": {
            "start": {
              "line": 17,
              "column": 19
            },
            "end": {
              "line": 17,
              "column": 29
            }
          },
          "extra": {
            "rawValue": "./comp17",
            "raw": "'./comp17'"
          },
          "value": "./comp17"
        }
      },
      {
        "type": "ExportNamedDeclaration",
        "start": 539,
        "end": 569,
        "loc": {
          "start": {
            "line": 18,
            "column": 0
          },
          "end": {
            "line": 18,
            "column": 30
          }
        },
        "specifiers": [
          {
            "type": "ExportDefaultSpecifier",
            "start": 546,
            "end": 552,
            "loc": {
              "start": {
                "line": 18,
                "column": 7
              },
              "end": {
                "line": 18,
                "column": 13
              }
            },
            "exported": {
              "type": "Identifier",
              "start": 546,
              "end": 552,
              "loc": {
                "start": {
                  "line": 18,
                  "column": 7
                },
                "end": {
                  "line": 18,
                  "column": 13
                },
                "identifierName": "comp18"
              },
              "name": "comp18"
            }
          }
        ],
        "source": {
          "type": "StringLiteral",
          "start": 558,
          "end": 568,
          "loc": {
            "start": {
              "line": 18,
              "column": 19
            },
            "end": {
              "line": 18,
              "column": 29
            }
          },
          "extra": {
            "rawValue": "./comp18",
            "raw": "'./comp18'"
          },
          "value": "./comp18"
        }
      },
      {
        "type": "ExportNamedDeclaration",
        "start": 570,
        "end": 600,
        "loc": {
          "start": {
            "line": 19,
            "column": 0
          },
          "end": {
            "line": 19,
            "column": 30
          }
        },
        "specifiers": [
          {
            "type": "ExportDefaultSpecifier",
            "start": 577,
            "end": 583,
            "loc": {
              "start": {
                "line": 19,
                "column": 7
              },
              "end": {
                "line": 19,
                "column": 13
              }
            },
            "exported": {
              "type": "Identifier",
              "start": 577,
              "end": 583,
              "loc": {
                "start": {
                  "line": 19,
                  "column": 7
                },
                "end": {
                  "line": 19,
                  "column": 13
                },
                "identifierName": "comp19"
              },
              "name": "comp19"
            }
          }
        ],
        "source": {
          "type": "StringLiteral",
          "start": 589,
          "end": 599,
          "loc": {
            "start": {
              "line": 19,
              "column": 19
            },
            "end": {
              "line": 19,
              "column": 29
            }
          },
          "extra": {
            "rawValue": "./comp19",
            "raw": "'./comp19'"
          },
          "value": "./comp19"
        }
      },
      {
        "type": "ExportNamedDeclaration",
        "start": 601,
        "end": 631,
        "loc": {
          "start": {
            "line": 20,
            "column": 0
          },
          "end": {
            "line": 20,
            "column": 30
          }
        },
        "specifiers": [
          {
            "type": "ExportDefaultSpecifier",
            "start": 608,
            "end": 614,
            "loc": {
              "start": {
                "line": 20,
                "column": 7
              },
              "end": {
                "line": 20,
                "column": 13
              }
            },
            "exported": {
              "type": "Identifier",
              "start": 608,
              "end": 614,
              "loc": {
                "start": {
                  "line": 20,
                  "column": 7
                },
                "end": {
                  "line": 20,
                  "column": 13
                },
                "identifierName": "comp20"
              },
              "name": "comp20"
            }
          }
        ],
        "source": {
          "type": "StringLiteral",
          "start": 620,
          "end": 630,
          "loc": {
            "start": {
              "line": 20,
              "column": 19
            },
            "end": {
              "line": 20,
              "column": 29
            }
          },
          "extra": {
            "rawValue": "./comp20",
            "raw": "'./comp20'"
          },
          "value": "./comp20"
        }
      },
      {
        "type": "ExportNamedDeclaration",
        "start": 632,
        "end": 662,
        "loc": {
          "start": {
            "line": 21,
            "column": 0
          },
          "end": {
            "line": 21,
            "column": 30
          }
        },
        "specifiers": [
          {
            "type": "ExportDefaultSpecifier",
            "start": 639,
            "end": 645,
            "loc": {
              "start": {
                "line": 21,
                "column": 7
              },
              "end": {
                "line": 21,
                "column": 13
              }
            },
            "exported": {
              "type": "Identifier",
              "start": 639,
              "end": 645,
              "loc": {
                "start": {
                  "line": 21,
                  "column": 7
                },
                "end": {
                  "line": 21,
                  "column": 13
                },
                "identifierName": "comp21"
              },
              "name": "comp21"
            }
          }
        ],
        "source": {
          "type": "StringLiteral",
          "start": 651,
          "end": 661,
          "loc": {
            "start": {
              "line": 21,
              "column": 19
            },
            "end": {
              "line": 21,
              "column": 29
            }
          },
          "extra": {
            "rawValue": "./comp21",
            "raw": "'./comp21'"
          },
          "value": "./comp21"
        }
      }
    ],
    "directives": []
  },
  "comments": [],
  "tokens": [
    {
      "type": {
        "label": "export",
        "keyword": "export",
        "beforeExpr": false,
        "startsExpr": false,
        "rightAssociative": false,
        "isLoop": false,
        "isAssign": false,
        "prefix": false,
        "postfix": false,
        "binop": null,
        "updateContext": null
      },
      "value": "export",
      "start": 0,
      "end": 6,
      "loc": {
        "start": {
          "line": 1,
          "column": 0
        },
        "end": {
          "line": 1,
          "column": 6
        }
      }
    },
    {
      "type": {
        "label": "name",
        "beforeExpr": false,
        "startsExpr": true,
        "rightAssociative": false,
        "isLoop": false,
        "isAssign": false,
        "prefix": false,
        "postfix": false,
        "binop": null
      },
      "value": "comp1",
      "start": 7,
      "end": 12,
      "loc": {
        "start": {
          "line": 1,
          "column": 7
        },
        "end": {
          "line": 1,
          "column": 12
        }
      }
    },
    {
      "type": {
        "label": "name",
        "beforeExpr": false,
        "startsExpr": true,
        "rightAssociative": false,
        "isLoop": false,
        "isAssign": false,
        "prefix": false,
        "postfix": false,
        "binop": null
      },
      "value": "from",
      "start": 13,
      "end": 17,
      "loc": {
        "start": {
          "line": 1,
          "column": 13
        },
        "end": {
          "line": 1,
          "column": 17
        }
      }
    },
    {
      "type": {
        "label": "string",
        "beforeExpr": false,
        "startsExpr": true,
        "rightAssociative": false,
        "isLoop": false,
        "isAssign": false,
        "prefix": false,
        "postfix": false,
        "binop": null,
        "updateContext": null
      },
      "value": "./comp1",
      "start": 18,
      "end": 27,
      "loc": {
        "start": {
          "line": 1,
          "column": 18
        },
        "end": {
          "line": 1,
          "column": 27
        }
      }
    },
    {
      "type": {
        "label": ";",
        "beforeExpr": true,
        "startsExpr": false,
        "rightAssociative": false,
        "isLoop": false,
        "isAssign": false,
        "prefix": false,
        "postfix": false,
        "binop": null,
        "updateContext": null
      },
      "start": 27,
      "end": 28,
      "loc": {
        "start": {
          "line": 1,
          "column": 27
        },
        "end": {
          "line": 1,
          "column": 28
        }
      }
    },
    {
      "type": {
        "label": "export",
        "keyword": "export",
        "beforeExpr": false,
        "startsExpr": false,
        "rightAssociative": false,
        "isLoop": false,
        "isAssign": false,
        "prefix": false,
        "postfix": false,
        "binop": null,
        "updateContext": null
      },
      "value": "export",
      "start": 29,
      "end": 35,
      "loc": {
        "start": {
          "line": 2,
          "column": 0
        },
        "end": {
          "line": 2,
          "column": 6
        }
      }
    },
    {
      "type": {
        "label": "name",
        "beforeExpr": false,
        "startsExpr": true,
        "rightAssociative": false,
        "isLoop": false,
        "isAssign": false,
        "prefix": false,
        "postfix": false,
        "binop": null
      },
      "value": "comp2",
      "start": 36,
      "end": 41,
      "loc": {
        "start": {
          "line": 2,
          "column": 7
        },
        "end": {
          "line": 2,
          "column": 12
        }
      }
    },
    {
      "type": {
        "label": "name",
        "beforeExpr": false,
        "startsExpr": true,
        "rightAssociative": false,
        "isLoop": false,
        "isAssign": false,
        "prefix": false,
        "postfix": false,
        "binop": null
      },
      "value": "from",
      "start": 42,
      "end": 46,
      "loc": {
        "start": {
          "line": 2,
          "column": 13
        },
        "end": {
          "line": 2,
          "column": 17
        }
      }
    },
    {
      "type": {
        "label": "string",
        "beforeExpr": false,
        "startsExpr": true,
        "rightAssociative": false,
        "isLoop": false,
        "isAssign": false,
        "prefix": false,
        "postfix": false,
        "binop": null,
        "updateContext": null
      },
      "value": "./comp2",
      "start": 47,
      "end": 56,
      "loc": {
        "start": {
          "line": 2,
          "column": 18
        },
        "end": {
          "line": 2,
          "column": 27
        }
      }
    },
    {
      "type": {
        "label": ";",
        "beforeExpr": true,
        "startsExpr": false,
        "rightAssociative": false,
        "isLoop": false,
        "isAssign": false,
        "prefix": false,
        "postfix": false,
        "binop": null,
        "updateContext": null
      },
      "start": 56,
      "end": 57,
      "loc": {
        "start": {
          "line": 2,
          "column": 27
        },
        "end": {
          "line": 2,
          "column": 28
        }
      }
    },
    {
      "type": {
        "label": "export",
        "keyword": "export",
        "beforeExpr": false,
        "startsExpr": false,
        "rightAssociative": false,
        "isLoop": false,
        "isAssign": false,
        "prefix": false,
        "postfix": false,
        "binop": null,
        "updateContext": null
      },
      "value": "export",
      "start": 58,
      "end": 64,
      "loc": {
        "start": {
          "line": 3,
          "column": 0
        },
        "end": {
          "line": 3,
          "column": 6
        }
      }
    },
    {
      "type": {
        "label": "{",
        "beforeExpr": true,
        "startsExpr": true,
        "rightAssociative": false,
        "isLoop": false,
        "isAssign": false,
        "prefix": false,
        "postfix": false,
        "binop": null
      },
      "start": 65,
      "end": 66,
      "loc": {
        "start": {
          "line": 3,
          "column": 7
        },
        "end": {
          "line": 3,
          "column": 8
        }
      }
    },
    {
      "type": {
        "label": "name",
        "beforeExpr": false,
        "startsExpr": true,
        "rightAssociative": false,
        "isLoop": false,
        "isAssign": false,
        "prefix": false,
        "postfix": false,
        "binop": null
      },
      "value": "multiSelect",
      "start": 67,
      "end": 78,
      "loc": {
        "start": {
          "line": 3,
          "column": 9
        },
        "end": {
          "line": 3,
          "column": 20
        }
      }
    },
    {
      "type": {
        "label": ",",
        "beforeExpr": true,
        "startsExpr": false,
        "rightAssociative": false,
        "isLoop": false,
        "isAssign": false,
        "prefix": false,
        "postfix": false,
        "binop": null,
        "updateContext": null
      },
      "start": 78,
      "end": 79,
      "loc": {
        "start": {
          "line": 3,
          "column": 20
        },
        "end": {
          "line": 3,
          "column": 21
        }
      }
    },
    {
      "type": {
        "label": "name",
        "beforeExpr": false,
        "startsExpr": true,
        "rightAssociative": false,
        "isLoop": false,
        "isAssign": false,
        "prefix": false,
        "postfix": false,
        "binop": null
      },
      "value": "multiSelectOptions",
      "start": 80,
      "end": 98,
      "loc": {
        "start": {
          "line": 3,
          "column": 22
        },
        "end": {
          "line": 3,
          "column": 40
        }
      }
    },
    {
      "type": {
        "label": "}",
        "beforeExpr": false,
        "startsExpr": false,
        "rightAssociative": false,
        "isLoop": false,
        "isAssign": false,
        "prefix": false,
        "postfix": false,
        "binop": null
      },
      "start": 99,
      "end": 100,
      "loc": {
        "start": {
          "line": 3,
          "column": 41
        },
        "end": {
          "line": 3,
          "column": 42
        }
      }
    },
    {
      "type": {
        "label": "name",
        "beforeExpr": false,
        "startsExpr": true,
        "rightAssociative": false,
        "isLoop": false,
        "isAssign": false,
        "prefix": false,
        "postfix": false,
        "binop": null
      },
      "value": "from",
      "start": 101,
      "end": 105,
      "loc": {
        "start": {
          "line": 3,
          "column": 43
        },
        "end": {
          "line": 3,
          "column": 47
        }
      }
    },
    {
      "type": {
        "label": "string",
        "beforeExpr": false,
        "startsExpr": true,
        "rightAssociative": false,
        "isLoop": false,
        "isAssign": false,
        "prefix": false,
        "postfix": false,
        "binop": null,
        "updateContext": null
      },
      "value": "./comp3",
      "start": 106,
      "end": 115,
      "loc": {
        "start": {
          "line": 3,
          "column": 48
        },
        "end": {
          "line": 3,
          "column": 57
        }
      }
    },
    {
      "type": {
        "label": ";",
        "beforeExpr": true,
        "startsExpr": false,
        "rightAssociative": false,
        "isLoop": false,
        "isAssign": false,
        "prefix": false,
        "postfix": false,
        "binop": null,
        "updateContext": null
      },
      "start": 115,
      "end": 116,
      "loc": {
        "start": {
          "line": 3,
          "column": 57
        },
        "end": {
          "line": 3,
          "column": 58
        }
      }
    },
    {
      "type": {
        "label": "export",
        "keyword": "export",
        "beforeExpr": false,
        "startsExpr": false,
        "rightAssociative": false,
        "isLoop": false,
        "isAssign": false,
        "prefix": false,
        "postfix": false,
        "binop": null,
        "updateContext": null
      },
      "value": "export",
      "start": 117,
      "end": 123,
      "loc": {
        "start": {
          "line": 4,
          "column": 0
        },
        "end": {
          "line": 4,
          "column": 6
        }
      }
    },
    {
      "type": {
        "label": "name",
        "beforeExpr": false,
        "startsExpr": true,
        "rightAssociative": false,
        "isLoop": false,
        "isAssign": false,
        "prefix": false,
        "postfix": false,
        "binop": null
      },
      "value": "comp4",
      "start": 124,
      "end": 129,
      "loc": {
        "start": {
          "line": 4,
          "column": 7
        },
        "end": {
          "line": 4,
          "column": 12
        }
      }
    },
    {
      "type": {
        "label": "name",
        "beforeExpr": false,
        "startsExpr": true,
        "rightAssociative": false,
        "isLoop": false,
        "isAssign": false,
        "prefix": false,
        "postfix": false,
        "binop": null
      },
      "value": "from",
      "start": 130,
      "end": 134,
      "loc": {
        "start": {
          "line": 4,
          "column": 13
        },
        "end": {
          "line": 4,
          "column": 17
        }
      }
    },
    {
      "type": {
        "label": "string",
        "beforeExpr": false,
        "startsExpr": true,
        "rightAssociative": false,
        "isLoop": false,
        "isAssign": false,
        "prefix": false,
        "postfix": false,
        "binop": null,
        "updateContext": null
      },
      "value": "./comp4",
      "start": 135,
      "end": 144,
      "loc": {
        "start": {
          "line": 4,
          "column": 18
        },
        "end": {
          "line": 4,
          "column": 27
        }
      }
    },
    {
      "type": {
        "label": ";",
        "beforeExpr": true,
        "startsExpr": false,
        "rightAssociative": false,
        "isLoop": false,
        "isAssign": false,
        "prefix": false,
        "postfix": false,
        "binop": null,
        "updateContext": null
      },
      "start": 144,
      "end": 145,
      "loc": {
        "start": {
          "line": 4,
          "column": 27
        },
        "end": {
          "line": 4,
          "column": 28
        }
      }
    },
    {
      "type": {
        "label": "export",
        "keyword": "export",
        "beforeExpr": false,
        "startsExpr": false,
        "rightAssociative": false,
        "isLoop": false,
        "isAssign": false,
        "prefix": false,
        "postfix": false,
        "binop": null,
        "updateContext": null
      },
      "value": "export",
      "start": 146,
      "end": 152,
      "loc": {
        "start": {
          "line": 5,
          "column": 0
        },
        "end": {
          "line": 5,
          "column": 6
        }
      }
    },
    {
      "type": {
        "label": "name",
        "beforeExpr": false,
        "startsExpr": true,
        "rightAssociative": false,
        "isLoop": false,
        "isAssign": false,
        "prefix": false,
        "postfix": false,
        "binop": null
      },
      "value": "comp5",
      "start": 153,
      "end": 158,
      "loc": {
        "start": {
          "line": 5,
          "column": 7
        },
        "end": {
          "line": 5,
          "column": 12
        }
      }
    },
    {
      "type": {
        "label": "name",
        "beforeExpr": false,
        "startsExpr": true,
        "rightAssociative": false,
        "isLoop": false,
        "isAssign": false,
        "prefix": false,
        "postfix": false,
        "binop": null
      },
      "value": "from",
      "start": 159,
      "end": 163,
      "loc": {
        "start": {
          "line": 5,
          "column": 13
        },
        "end": {
          "line": 5,
          "column": 17
        }
      }
    },
    {
      "type": {
        "label": "string",
        "beforeExpr": false,
        "startsExpr": true,
        "rightAssociative": false,
        "isLoop": false,
        "isAssign": false,
        "prefix": false,
        "postfix": false,
        "binop": null,
        "updateContext": null
      },
      "value": "./comp5",
      "start": 164,
      "end": 173,
      "loc": {
        "start": {
          "line": 5,
          "column": 18
        },
        "end": {
          "line": 5,
          "column": 27
        }
      }
    },
    {
      "type": {
        "label": ";",
        "beforeExpr": true,
        "startsExpr": false,
        "rightAssociative": false,
        "isLoop": false,
        "isAssign": false,
        "prefix": false,
        "postfix": false,
        "binop": null,
        "updateContext": null
      },
      "start": 173,
      "end": 174,
      "loc": {
        "start": {
          "line": 5,
          "column": 27
        },
        "end": {
          "line": 5,
          "column": 28
        }
      }
    },
    {
      "type": {
        "label": "export",
        "keyword": "export",
        "beforeExpr": false,
        "startsExpr": false,
        "rightAssociative": false,
        "isLoop": false,
        "isAssign": false,
        "prefix": false,
        "postfix": false,
        "binop": null,
        "updateContext": null
      },
      "value": "export",
      "start": 175,
      "end": 181,
      "loc": {
        "start": {
          "line": 6,
          "column": 0
        },
        "end": {
          "line": 6,
          "column": 6
        }
      }
    },
    {
      "type": {
        "label": "name",
        "beforeExpr": false,
        "startsExpr": true,
        "rightAssociative": false,
        "isLoop": false,
        "isAssign": false,
        "prefix": false,
        "postfix": false,
        "binop": null
      },
      "value": "comp6",
      "start": 182,
      "end": 187,
      "loc": {
        "start": {
          "line": 6,
          "column": 7
        },
        "end": {
          "line": 6,
          "column": 12
        }
      }
    },
    {
      "type": {
        "label": "name",
        "beforeExpr": false,
        "startsExpr": true,
        "rightAssociative": false,
        "isLoop": false,
        "isAssign": false,
        "prefix": false,
        "postfix": false,
        "binop": null
      },
      "value": "from",
      "start": 188,
      "end": 192,
      "loc": {
        "start": {
          "line": 6,
          "column": 13
        },
        "end": {
          "line": 6,
          "column": 17
        }
      }
    },
    {
      "type": {
        "label": "string",
        "beforeExpr": false,
        "startsExpr": true,
        "rightAssociative": false,
        "isLoop": false,
        "isAssign": false,
        "prefix": false,
        "postfix": false,
        "binop": null,
        "updateContext": null
      },
      "value": "./comp6",
      "start": 193,
      "end": 202,
      "loc": {
        "start": {
          "line": 6,
          "column": 18
        },
        "end": {
          "line": 6,
          "column": 27
        }
      }
    },
    {
      "type": {
        "label": ";",
        "beforeExpr": true,
        "startsExpr": false,
        "rightAssociative": false,
        "isLoop": false,
        "isAssign": false,
        "prefix": false,
        "postfix": false,
        "binop": null,
        "updateContext": null
      },
      "start": 202,
      "end": 203,
      "loc": {
        "start": {
          "line": 6,
          "column": 27
        },
        "end": {
          "line": 6,
          "column": 28
        }
      }
    },
    {
      "type": {
        "label": "export",
        "keyword": "export",
        "beforeExpr": false,
        "startsExpr": false,
        "rightAssociative": false,
        "isLoop": false,
        "isAssign": false,
        "prefix": false,
        "postfix": false,
        "binop": null,
        "updateContext": null
      },
      "value": "export",
      "start": 204,
      "end": 210,
      "loc": {
        "start": {
          "line": 7,
          "column": 0
        },
        "end": {
          "line": 7,
          "column": 6
        }
      }
    },
    {
      "type": {
        "label": "name",
        "beforeExpr": false,
        "startsExpr": true,
        "rightAssociative": false,
        "isLoop": false,
        "isAssign": false,
        "prefix": false,
        "postfix": false,
        "binop": null
      },
      "value": "comp7",
      "start": 211,
      "end": 216,
      "loc": {
        "start": {
          "line": 7,
          "column": 7
        },
        "end": {
          "line": 7,
          "column": 12
        }
      }
    },
    {
      "type": {
        "label": "name",
        "beforeExpr": false,
        "startsExpr": true,
        "rightAssociative": false,
        "isLoop": false,
        "isAssign": false,
        "prefix": false,
        "postfix": false,
        "binop": null
      },
      "value": "from",
      "start": 217,
      "end": 221,
      "loc": {
        "start": {
          "line": 7,
          "column": 13
        },
        "end": {
          "line": 7,
          "column": 17
        }
      }
    },
    {
      "type": {
        "label": "string",
        "beforeExpr": false,
        "startsExpr": true,
        "rightAssociative": false,
        "isLoop": false,
        "isAssign": false,
        "prefix": false,
        "postfix": false,
        "binop": null,
        "updateContext": null
      },
      "value": "./comp7",
      "start": 222,
      "end": 231,
      "loc": {
        "start": {
          "line": 7,
          "column": 18
        },
        "end": {
          "line": 7,
          "column": 27
        }
      }
    },
    {
      "type": {
        "label": ";",
        "beforeExpr": true,
        "startsExpr": false,
        "rightAssociative": false,
        "isLoop": false,
        "isAssign": false,
        "prefix": false,
        "postfix": false,
        "binop": null,
        "updateContext": null
      },
      "start": 231,
      "end": 232,
      "loc": {
        "start": {
          "line": 7,
          "column": 27
        },
        "end": {
          "line": 7,
          "column": 28
        }
      }
    },
    {
      "type": {
        "label": "export",
        "keyword": "export",
        "beforeExpr": false,
        "startsExpr": false,
        "rightAssociative": false,
        "isLoop": false,
        "isAssign": false,
        "prefix": false,
        "postfix": false,
        "binop": null,
        "updateContext": null
      },
      "value": "export",
      "start": 233,
      "end": 239,
      "loc": {
        "start": {
          "line": 8,
          "column": 0
        },
        "end": {
          "line": 8,
          "column": 6
        }
      }
    },
    {
      "type": {
        "label": "name",
        "beforeExpr": false,
        "startsExpr": true,
        "rightAssociative": false,
        "isLoop": false,
        "isAssign": false,
        "prefix": false,
        "postfix": false,
        "binop": null
      },
      "value": "comp8",
      "start": 240,
      "end": 245,
      "loc": {
        "start": {
          "line": 8,
          "column": 7
        },
        "end": {
          "line": 8,
          "column": 12
        }
      }
    },
    {
      "type": {
        "label": "name",
        "beforeExpr": false,
        "startsExpr": true,
        "rightAssociative": false,
        "isLoop": false,
        "isAssign": false,
        "prefix": false,
        "postfix": false,
        "binop": null
      },
      "value": "from",
      "start": 246,
      "end": 250,
      "loc": {
        "start": {
          "line": 8,
          "column": 13
        },
        "end": {
          "line": 8,
          "column": 17
        }
      }
    },
    {
      "type": {
        "label": "string",
        "beforeExpr": false,
        "startsExpr": true,
        "rightAssociative": false,
        "isLoop": false,
        "isAssign": false,
        "prefix": false,
        "postfix": false,
        "binop": null,
        "updateContext": null
      },
      "value": "./comp8",
      "start": 251,
      "end": 260,
      "loc": {
        "start": {
          "line": 8,
          "column": 18
        },
        "end": {
          "line": 8,
          "column": 27
        }
      }
    },
    {
      "type": {
        "label": ";",
        "beforeExpr": true,
        "startsExpr": false,
        "rightAssociative": false,
        "isLoop": false,
        "isAssign": false,
        "prefix": false,
        "postfix": false,
        "binop": null,
        "updateContext": null
      },
      "start": 260,
      "end": 261,
      "loc": {
        "start": {
          "line": 8,
          "column": 27
        },
        "end": {
          "line": 8,
          "column": 28
        }
      }
    },
    {
      "type": {
        "label": "export",
        "keyword": "export",
        "beforeExpr": false,
        "startsExpr": false,
        "rightAssociative": false,
        "isLoop": false,
        "isAssign": false,
        "prefix": false,
        "postfix": false,
        "binop": null,
        "updateContext": null
      },
      "value": "export",
      "start": 262,
      "end": 268,
      "loc": {
        "start": {
          "line": 9,
          "column": 0
        },
        "end": {
          "line": 9,
          "column": 6
        }
      }
    },
    {
      "type": {
        "label": "name",
        "beforeExpr": false,
        "startsExpr": true,
        "rightAssociative": false,
        "isLoop": false,
        "isAssign": false,
        "prefix": false,
        "postfix": false,
        "binop": null
      },
      "value": "comp9",
      "start": 269,
      "end": 274,
      "loc": {
        "start": {
          "line": 9,
          "column": 7
        },
        "end": {
          "line": 9,
          "column": 12
        }
      }
    },
    {
      "type": {
        "label": "name",
        "beforeExpr": false,
        "startsExpr": true,
        "rightAssociative": false,
        "isLoop": false,
        "isAssign": false,
        "prefix": false,
        "postfix": false,
        "binop": null
      },
      "value": "from",
      "start": 275,
      "end": 279,
      "loc": {
        "start": {
          "line": 9,
          "column": 13
        },
        "end": {
          "line": 9,
          "column": 17
        }
      }
    },
    {
      "type": {
        "label": "string",
        "beforeExpr": false,
        "startsExpr": true,
        "rightAssociative": false,
        "isLoop": false,
        "isAssign": false,
        "prefix": false,
        "postfix": false,
        "binop": null,
        "updateContext": null
      },
      "value": "./comp9",
      "start": 280,
      "end": 289,
      "loc": {
        "start": {
          "line": 9,
          "column": 18
        },
        "end": {
          "line": 9,
          "column": 27
        }
      }
    },
    {
      "type": {
        "label": ";",
        "beforeExpr": true,
        "startsExpr": false,
        "rightAssociative": false,
        "isLoop": false,
        "isAssign": false,
        "prefix": false,
        "postfix": false,
        "binop": null,
        "updateContext": null
      },
      "start": 289,
      "end": 290,
      "loc": {
        "start": {
          "line": 9,
          "column": 27
        },
        "end": {
          "line": 9,
          "column": 28
        }
      }
    },
    {
      "type": {
        "label": "export",
        "keyword": "export",
        "beforeExpr": false,
        "startsExpr": false,
        "rightAssociative": false,
        "isLoop": false,
        "isAssign": false,
        "prefix": false,
        "postfix": false,
        "binop": null,
        "updateContext": null
      },
      "value": "export",
      "start": 291,
      "end": 297,
      "loc": {
        "start": {
          "line": 10,
          "column": 0
        },
        "end": {
          "line": 10,
          "column": 6
        }
      }
    },
    {
      "type": {
        "label": "name",
        "beforeExpr": false,
        "startsExpr": true,
        "rightAssociative": false,
        "isLoop": false,
        "isAssign": false,
        "prefix": false,
        "postfix": false,
        "binop": null
      },
      "value": "comp10",
      "start": 298,
      "end": 304,
      "loc": {
        "start": {
          "line": 10,
          "column": 7
        },
        "end": {
          "line": 10,
          "column": 13
        }
      }
    },
    {
      "type": {
        "label": "name",
        "beforeExpr": false,
        "startsExpr": true,
        "rightAssociative": false,
        "isLoop": false,
        "isAssign": false,
        "prefix": false,
        "postfix": false,
        "binop": null
      },
      "value": "from",
      "start": 305,
      "end": 309,
      "loc": {
        "start": {
          "line": 10,
          "column": 14
        },
        "end": {
          "line": 10,
          "column": 18
        }
      }
    },
    {
      "type": {
        "label": "string",
        "beforeExpr": false,
        "startsExpr": true,
        "rightAssociative": false,
        "isLoop": false,
        "isAssign": false,
        "prefix": false,
        "postfix": false,
        "binop": null,
        "updateContext": null
      },
      "value": "./comp10",
      "start": 310,
      "end": 320,
      "loc": {
        "start": {
          "line": 10,
          "column": 19
        },
        "end": {
          "line": 10,
          "column": 29
        }
      }
    },
    {
      "type": {
        "label": ";",
        "beforeExpr": true,
        "startsExpr": false,
        "rightAssociative": false,
        "isLoop": false,
        "isAssign": false,
        "prefix": false,
        "postfix": false,
        "binop": null,
        "updateContext": null
      },
      "start": 320,
      "end": 321,
      "loc": {
        "start": {
          "line": 10,
          "column": 29
        },
        "end": {
          "line": 10,
          "column": 30
        }
      }
    },
    {
      "type": {
        "label": "export",
        "keyword": "export",
        "beforeExpr": false,
        "startsExpr": false,
        "rightAssociative": false,
        "isLoop": false,
        "isAssign": false,
        "prefix": false,
        "postfix": false,
        "binop": null,
        "updateContext": null
      },
      "value": "export",
      "start": 322,
      "end": 328,
      "loc": {
        "start": {
          "line": 11,
          "column": 0
        },
        "end": {
          "line": 11,
          "column": 6
        }
      }
    },
    {
      "type": {
        "label": "name",
        "beforeExpr": false,
        "startsExpr": true,
        "rightAssociative": false,
        "isLoop": false,
        "isAssign": false,
        "prefix": false,
        "postfix": false,
        "binop": null
      },
      "value": "comp11",
      "start": 329,
      "end": 335,
      "loc": {
        "start": {
          "line": 11,
          "column": 7
        },
        "end": {
          "line": 11,
          "column": 13
        }
      }
    },
    {
      "type": {
        "label": "name",
        "beforeExpr": false,
        "startsExpr": true,
        "rightAssociative": false,
        "isLoop": false,
        "isAssign": false,
        "prefix": false,
        "postfix": false,
        "binop": null
      },
      "value": "from",
      "start": 336,
      "end": 340,
      "loc": {
        "start": {
          "line": 11,
          "column": 14
        },
        "end": {
          "line": 11,
          "column": 18
        }
      }
    },
    {
      "type": {
        "label": "string",
        "beforeExpr": false,
        "startsExpr": true,
        "rightAssociative": false,
        "isLoop": false,
        "isAssign": false,
        "prefix": false,
        "postfix": false,
        "binop": null,
        "updateContext": null
      },
      "value": "./comp11",
      "start": 341,
      "end": 351,
      "loc": {
        "start": {
          "line": 11,
          "column": 19
        },
        "end": {
          "line": 11,
          "column": 29
        }
      }
    },
    {
      "type": {
        "label": ";",
        "beforeExpr": true,
        "startsExpr": false,
        "rightAssociative": false,
        "isLoop": false,
        "isAssign": false,
        "prefix": false,
        "postfix": false,
        "binop": null,
        "updateContext": null
      },
      "start": 351,
      "end": 352,
      "loc": {
        "start": {
          "line": 11,
          "column": 29
        },
        "end": {
          "line": 11,
          "column": 30
        }
      }
    },
    {
      "type": {
        "label": "export",
        "keyword": "export",
        "beforeExpr": false,
        "startsExpr": false,
        "rightAssociative": false,
        "isLoop": false,
        "isAssign": false,
        "prefix": false,
        "postfix": false,
        "binop": null,
        "updateContext": null
      },
      "value": "export",
      "start": 353,
      "end": 359,
      "loc": {
        "start": {
          "line": 12,
          "column": 0
        },
        "end": {
          "line": 12,
          "column": 6
        }
      }
    },
    {
      "type": {
        "label": "name",
        "beforeExpr": false,
        "startsExpr": true,
        "rightAssociative": false,
        "isLoop": false,
        "isAssign": false,
        "prefix": false,
        "postfix": false,
        "binop": null
      },
      "value": "comp12",
      "start": 360,
      "end": 366,
      "loc": {
        "start": {
          "line": 12,
          "column": 7
        },
        "end": {
          "line": 12,
          "column": 13
        }
      }
    },
    {
      "type": {
        "label": "name",
        "beforeExpr": false,
        "startsExpr": true,
        "rightAssociative": false,
        "isLoop": false,
        "isAssign": false,
        "prefix": false,
        "postfix": false,
        "binop": null
      },
      "value": "from",
      "start": 367,
      "end": 371,
      "loc": {
        "start": {
          "line": 12,
          "column": 14
        },
        "end": {
          "line": 12,
          "column": 18
        }
      }
    },
    {
      "type": {
        "label": "string",
        "beforeExpr": false,
        "startsExpr": true,
        "rightAssociative": false,
        "isLoop": false,
        "isAssign": false,
        "prefix": false,
        "postfix": false,
        "binop": null,
        "updateContext": null
      },
      "value": "./comp12",
      "start": 372,
      "end": 382,
      "loc": {
        "start": {
          "line": 12,
          "column": 19
        },
        "end": {
          "line": 12,
          "column": 29
        }
      }
    },
    {
      "type": {
        "label": ";",
        "beforeExpr": true,
        "startsExpr": false,
        "rightAssociative": false,
        "isLoop": false,
        "isAssign": false,
        "prefix": false,
        "postfix": false,
        "binop": null,
        "updateContext": null
      },
      "start": 382,
      "end": 383,
      "loc": {
        "start": {
          "line": 12,
          "column": 29
        },
        "end": {
          "line": 12,
          "column": 30
        }
      }
    },
    {
      "type": {
        "label": "export",
        "keyword": "export",
        "beforeExpr": false,
        "startsExpr": false,
        "rightAssociative": false,
        "isLoop": false,
        "isAssign": false,
        "prefix": false,
        "postfix": false,
        "binop": null,
        "updateContext": null
      },
      "value": "export",
      "start": 384,
      "end": 390,
      "loc": {
        "start": {
          "line": 13,
          "column": 0
        },
        "end": {
          "line": 13,
          "column": 6
        }
      }
    },
    {
      "type": {
        "label": "name",
        "beforeExpr": false,
        "startsExpr": true,
        "rightAssociative": false,
        "isLoop": false,
        "isAssign": false,
        "prefix": false,
        "postfix": false,
        "binop": null
      },
      "value": "comp13",
      "start": 391,
      "end": 397,
      "loc": {
        "start": {
          "line": 13,
          "column": 7
        },
        "end": {
          "line": 13,
          "column": 13
        }
      }
    },
    {
      "type": {
        "label": "name",
        "beforeExpr": false,
        "startsExpr": true,
        "rightAssociative": false,
        "isLoop": false,
        "isAssign": false,
        "prefix": false,
        "postfix": false,
        "binop": null
      },
      "value": "from",
      "start": 398,
      "end": 402,
      "loc": {
        "start": {
          "line": 13,
          "column": 14
        },
        "end": {
          "line": 13,
          "column": 18
        }
      }
    },
    {
      "type": {
        "label": "string",
        "beforeExpr": false,
        "startsExpr": true,
        "rightAssociative": false,
        "isLoop": false,
        "isAssign": false,
        "prefix": false,
        "postfix": false,
        "binop": null,
        "updateContext": null
      },
      "value": "./comp13",
      "start": 403,
      "end": 413,
      "loc": {
        "start": {
          "line": 13,
          "column": 19
        },
        "end": {
          "line": 13,
          "column": 29
        }
      }
    },
    {
      "type": {
        "label": ";",
        "beforeExpr": true,
        "startsExpr": false,
        "rightAssociative": false,
        "isLoop": false,
        "isAssign": false,
        "prefix": false,
        "postfix": false,
        "binop": null,
        "updateContext": null
      },
      "start": 413,
      "end": 414,
      "loc": {
        "start": {
          "line": 13,
          "column": 29
        },
        "end": {
          "line": 13,
          "column": 30
        }
      }
    },
    {
      "type": {
        "label": "export",
        "keyword": "export",
        "beforeExpr": false,
        "startsExpr": false,
        "rightAssociative": false,
        "isLoop": false,
        "isAssign": false,
        "prefix": false,
        "postfix": false,
        "binop": null,
        "updateContext": null
      },
      "value": "export",
      "start": 415,
      "end": 421,
      "loc": {
        "start": {
          "line": 14,
          "column": 0
        },
        "end": {
          "line": 14,
          "column": 6
        }
      }
    },
    {
      "type": {
        "label": "name",
        "beforeExpr": false,
        "startsExpr": true,
        "rightAssociative": false,
        "isLoop": false,
        "isAssign": false,
        "prefix": false,
        "postfix": false,
        "binop": null
      },
      "value": "comp14",
      "start": 422,
      "end": 428,
      "loc": {
        "start": {
          "line": 14,
          "column": 7
        },
        "end": {
          "line": 14,
          "column": 13
        }
      }
    },
    {
      "type": {
        "label": "name",
        "beforeExpr": false,
        "startsExpr": true,
        "rightAssociative": false,
        "isLoop": false,
        "isAssign": false,
        "prefix": false,
        "postfix": false,
        "binop": null
      },
      "value": "from",
      "start": 429,
      "end": 433,
      "loc": {
        "start": {
          "line": 14,
          "column": 14
        },
        "end": {
          "line": 14,
          "column": 18
        }
      }
    },
    {
      "type": {
        "label": "string",
        "beforeExpr": false,
        "startsExpr": true,
        "rightAssociative": false,
        "isLoop": false,
        "isAssign": false,
        "prefix": false,
        "postfix": false,
        "binop": null,
        "updateContext": null
      },
      "value": "./comp14",
      "start": 434,
      "end": 444,
      "loc": {
        "start": {
          "line": 14,
          "column": 19
        },
        "end": {
          "line": 14,
          "column": 29
        }
      }
    },
    {
      "type": {
        "label": ";",
        "beforeExpr": true,
        "startsExpr": false,
        "rightAssociative": false,
        "isLoop": false,
        "isAssign": false,
        "prefix": false,
        "postfix": false,
        "binop": null,
        "updateContext": null
      },
      "start": 444,
      "end": 445,
      "loc": {
        "start": {
          "line": 14,
          "column": 29
        },
        "end": {
          "line": 14,
          "column": 30
        }
      }
    },
    {
      "type": {
        "label": "export",
        "keyword": "export",
        "beforeExpr": false,
        "startsExpr": false,
        "rightAssociative": false,
        "isLoop": false,
        "isAssign": false,
        "prefix": false,
        "postfix": false,
        "binop": null,
        "updateContext": null
      },
      "value": "export",
      "start": 446,
      "end": 452,
      "loc": {
        "start": {
          "line": 15,
          "column": 0
        },
        "end": {
          "line": 15,
          "column": 6
        }
      }
    },
    {
      "type": {
        "label": "name",
        "beforeExpr": false,
        "startsExpr": true,
        "rightAssociative": false,
        "isLoop": false,
        "isAssign": false,
        "prefix": false,
        "postfix": false,
        "binop": null
      },
      "value": "comp15",
      "start": 453,
      "end": 459,
      "loc": {
        "start": {
          "line": 15,
          "column": 7
        },
        "end": {
          "line": 15,
          "column": 13
        }
      }
    },
    {
      "type": {
        "label": "name",
        "beforeExpr": false,
        "startsExpr": true,
        "rightAssociative": false,
        "isLoop": false,
        "isAssign": false,
        "prefix": false,
        "postfix": false,
        "binop": null
      },
      "value": "from",
      "start": 460,
      "end": 464,
      "loc": {
        "start": {
          "line": 15,
          "column": 14
        },
        "end": {
          "line": 15,
          "column": 18
        }
      }
    },
    {
      "type": {
        "label": "string",
        "beforeExpr": false,
        "startsExpr": true,
        "rightAssociative": false,
        "isLoop": false,
        "isAssign": false,
        "prefix": false,
        "postfix": false,
        "binop": null,
        "updateContext": null
      },
      "value": "./comp15",
      "start": 465,
      "end": 475,
      "loc": {
        "start": {
          "line": 15,
          "column": 19
        },
        "end": {
          "line": 15,
          "column": 29
        }
      }
    },
    {
      "type": {
        "label": ";",
        "beforeExpr": true,
        "startsExpr": false,
        "rightAssociative": false,
        "isLoop": false,
        "isAssign": false,
        "prefix": false,
        "postfix": false,
        "binop": null,
        "updateContext": null
      },
      "start": 475,
      "end": 476,
      "loc": {
        "start": {
          "line": 15,
          "column": 29
        },
        "end": {
          "line": 15,
          "column": 30
        }
      }
    },
    {
      "type": {
        "label": "export",
        "keyword": "export",
        "beforeExpr": false,
        "startsExpr": false,
        "rightAssociative": false,
        "isLoop": false,
        "isAssign": false,
        "prefix": false,
        "postfix": false,
        "binop": null,
        "updateContext": null
      },
      "value": "export",
      "start": 477,
      "end": 483,
      "loc": {
        "start": {
          "line": 16,
          "column": 0
        },
        "end": {
          "line": 16,
          "column": 6
        }
      }
    },
    {
      "type": {
        "label": "name",
        "beforeExpr": false,
        "startsExpr": true,
        "rightAssociative": false,
        "isLoop": false,
        "isAssign": false,
        "prefix": false,
        "postfix": false,
        "binop": null
      },
      "value": "comp16",
      "start": 484,
      "end": 490,
      "loc": {
        "start": {
          "line": 16,
          "column": 7
        },
        "end": {
          "line": 16,
          "column": 13
        }
      }
    },
    {
      "type": {
        "label": "name",
        "beforeExpr": false,
        "startsExpr": true,
        "rightAssociative": false,
        "isLoop": false,
        "isAssign": false,
        "prefix": false,
        "postfix": false,
        "binop": null
      },
      "value": "from",
      "start": 491,
      "end": 495,
      "loc": {
        "start": {
          "line": 16,
          "column": 14
        },
        "end": {
          "line": 16,
          "column": 18
        }
      }
    },
    {
      "type": {
        "label": "string",
        "beforeExpr": false,
        "startsExpr": true,
        "rightAssociative": false,
        "isLoop": false,
        "isAssign": false,
        "prefix": false,
        "postfix": false,
        "binop": null,
        "updateContext": null
      },
      "value": "./comp16",
      "start": 496,
      "end": 506,
      "loc": {
        "start": {
          "line": 16,
          "column": 19
        },
        "end": {
          "line": 16,
          "column": 29
        }
      }
    },
    {
      "type": {
        "label": ";",
        "beforeExpr": true,
        "startsExpr": false,
        "rightAssociative": false,
        "isLoop": false,
        "isAssign": false,
        "prefix": false,
        "postfix": false,
        "binop": null,
        "updateContext": null
      },
      "start": 506,
      "end": 507,
      "loc": {
        "start": {
          "line": 16,
          "column": 29
        },
        "end": {
          "line": 16,
          "column": 30
        }
      }
    },
    {
      "type": {
        "label": "export",
        "keyword": "export",
        "beforeExpr": false,
        "startsExpr": false,
        "rightAssociative": false,
        "isLoop": false,
        "isAssign": false,
        "prefix": false,
        "postfix": false,
        "binop": null,
        "updateContext": null
      },
      "value": "export",
      "start": 508,
      "end": 514,
      "loc": {
        "start": {
          "line": 17,
          "column": 0
        },
        "end": {
          "line": 17,
          "column": 6
        }
      }
    },
    {
      "type": {
        "label": "name",
        "beforeExpr": false,
        "startsExpr": true,
        "rightAssociative": false,
        "isLoop": false,
        "isAssign": false,
        "prefix": false,
        "postfix": false,
        "binop": null
      },
      "value": "comp17",
      "start": 515,
      "end": 521,
      "loc": {
        "start": {
          "line": 17,
          "column": 7
        },
        "end": {
          "line": 17,
          "column": 13
        }
      }
    },
    {
      "type": {
        "label": "name",
        "beforeExpr": false,
        "startsExpr": true,
        "rightAssociative": false,
        "isLoop": false,
        "isAssign": false,
        "prefix": false,
        "postfix": false,
        "binop": null
      },
      "value": "from",
      "start": 522,
      "end": 526,
      "loc": {
        "start": {
          "line": 17,
          "column": 14
        },
        "end": {
          "line": 17,
          "column": 18
        }
      }
    },
    {
      "type": {
        "label": "string",
        "beforeExpr": false,
        "startsExpr": true,
        "rightAssociative": false,
        "isLoop": false,
        "isAssign": false,
        "prefix": false,
        "postfix": false,
        "binop": null,
        "updateContext": null
      },
      "value": "./comp17",
      "start": 527,
      "end": 537,
      "loc": {
        "start": {
          "line": 17,
          "column": 19
        },
        "end": {
          "line": 17,
          "column": 29
        }
      }
    },
    {
      "type": {
        "label": ";",
        "beforeExpr": true,
        "startsExpr": false,
        "rightAssociative": false,
        "isLoop": false,
        "isAssign": false,
        "prefix": false,
        "postfix": false,
        "binop": null,
        "updateContext": null
      },
      "start": 537,
      "end": 538,
      "loc": {
        "start": {
          "line": 17,
          "column": 29
        },
        "end": {
          "line": 17,
          "column": 30
        }
      }
    },
    {
      "type": {
        "label": "export",
        "keyword": "export",
        "beforeExpr": false,
        "startsExpr": false,
        "rightAssociative": false,
        "isLoop": false,
        "isAssign": false,
        "prefix": false,
        "postfix": false,
        "binop": null,
        "updateContext": null
      },
      "value": "export",
      "start": 539,
      "end": 545,
      "loc": {
        "start": {
          "line": 18,
          "column": 0
        },
        "end": {
          "line": 18,
          "column": 6
        }
      }
    },
    {
      "type": {
        "label": "name",
        "beforeExpr": false,
        "startsExpr": true,
        "rightAssociative": false,
        "isLoop": false,
        "isAssign": false,
        "prefix": false,
        "postfix": false,
        "binop": null
      },
      "value": "comp18",
      "start": 546,
      "end": 552,
      "loc": {
        "start": {
          "line": 18,
          "column": 7
        },
        "end": {
          "line": 18,
          "column": 13
        }
      }
    },
    {
      "type": {
        "label": "name",
        "beforeExpr": false,
        "startsExpr": true,
        "rightAssociative": false,
        "isLoop": false,
        "isAssign": false,
        "prefix": false,
        "postfix": false,
        "binop": null
      },
      "value": "from",
      "start": 553,
      "end": 557,
      "loc": {
        "start": {
          "line": 18,
          "column": 14
        },
        "end": {
          "line": 18,
          "column": 18
        }
      }
    },
    {
      "type": {
        "label": "string",
        "beforeExpr": false,
        "startsExpr": true,
        "rightAssociative": false,
        "isLoop": false,
        "isAssign": false,
        "prefix": false,
        "postfix": false,
        "binop": null,
        "updateContext": null
      },
      "value": "./comp18",
      "start": 558,
      "end": 568,
      "loc": {
        "start": {
          "line": 18,
          "column": 19
        },
        "end": {
          "line": 18,
          "column": 29
        }
      }
    },
    {
      "type": {
        "label": ";",
        "beforeExpr": true,
        "startsExpr": false,
        "rightAssociative": false,
        "isLoop": false,
        "isAssign": false,
        "prefix": false,
        "postfix": false,
        "binop": null,
        "updateContext": null
      },
      "start": 568,
      "end": 569,
      "loc": {
        "start": {
          "line": 18,
          "column": 29
        },
        "end": {
          "line": 18,
          "column": 30
        }
      }
    },
    {
      "type": {
        "label": "export",
        "keyword": "export",
        "beforeExpr": false,
        "startsExpr": false,
        "rightAssociative": false,
        "isLoop": false,
        "isAssign": false,
        "prefix": false,
        "postfix": false,
        "binop": null,
        "updateContext": null
      },
      "value": "export",
      "start": 570,
      "end": 576,
      "loc": {
        "start": {
          "line": 19,
          "column": 0
        },
        "end": {
          "line": 19,
          "column": 6
        }
      }
    },
    {
      "type": {
        "label": "name",
        "beforeExpr": false,
        "startsExpr": true,
        "rightAssociative": false,
        "isLoop": false,
        "isAssign": false,
        "prefix": false,
        "postfix": false,
        "binop": null
      },
      "value": "comp19",
      "start": 577,
      "end": 583,
      "loc": {
        "start": {
          "line": 19,
          "column": 7
        },
        "end": {
          "line": 19,
          "column": 13
        }
      }
    },
    {
      "type": {
        "label": "name",
        "beforeExpr": false,
        "startsExpr": true,
        "rightAssociative": false,
        "isLoop": false,
        "isAssign": false,
        "prefix": false,
        "postfix": false,
        "binop": null
      },
      "value": "from",
      "start": 584,
      "end": 588,
      "loc": {
        "start": {
          "line": 19,
          "column": 14
        },
        "end": {
          "line": 19,
          "column": 18
        }
      }
    },
    {
      "type": {
        "label": "string",
        "beforeExpr": false,
        "startsExpr": true,
        "rightAssociative": false,
        "isLoop": false,
        "isAssign": false,
        "prefix": false,
        "postfix": false,
        "binop": null,
        "updateContext": null
      },
      "value": "./comp19",
      "start": 589,
      "end": 599,
      "loc": {
        "start": {
          "line": 19,
          "column": 19
        },
        "end": {
          "line": 19,
          "column": 29
        }
      }
    },
    {
      "type": {
        "label": ";",
        "beforeExpr": true,
        "startsExpr": false,
        "rightAssociative": false,
        "isLoop": false,
        "isAssign": false,
        "prefix": false,
        "postfix": false,
        "binop": null,
        "updateContext": null
      },
      "start": 599,
      "end": 600,
      "loc": {
        "start": {
          "line": 19,
          "column": 29
        },
        "end": {
          "line": 19,
          "column": 30
        }
      }
    },
    {
      "type": {
        "label": "export",
        "keyword": "export",
        "beforeExpr": false,
        "startsExpr": false,
        "rightAssociative": false,
        "isLoop": false,
        "isAssign": false,
        "prefix": false,
        "postfix": false,
        "binop": null,
        "updateContext": null
      },
      "value": "export",
      "start": 601,
      "end": 607,
      "loc": {
        "start": {
          "line": 20,
          "column": 0
        },
        "end": {
          "line": 20,
          "column": 6
        }
      }
    },
    {
      "type": {
        "label": "name",
        "beforeExpr": false,
        "startsExpr": true,
        "rightAssociative": false,
        "isLoop": false,
        "isAssign": false,
        "prefix": false,
        "postfix": false,
        "binop": null
      },
      "value": "comp20",
      "start": 608,
      "end": 614,
      "loc": {
        "start": {
          "line": 20,
          "column": 7
        },
        "end": {
          "line": 20,
          "column": 13
        }
      }
    },
    {
      "type": {
        "label": "name",
        "beforeExpr": false,
        "startsExpr": true,
        "rightAssociative": false,
        "isLoop": false,
        "isAssign": false,
        "prefix": false,
        "postfix": false,
        "binop": null
      },
      "value": "from",
      "start": 615,
      "end": 619,
      "loc": {
        "start": {
          "line": 20,
          "column": 14
        },
        "end": {
          "line": 20,
          "column": 18
        }
      }
    },
    {
      "type": {
        "label": "string",
        "beforeExpr": false,
        "startsExpr": true,
        "rightAssociative": false,
        "isLoop": false,
        "isAssign": false,
        "prefix": false,
        "postfix": false,
        "binop": null,
        "updateContext": null
      },
      "value": "./comp20",
      "start": 620,
      "end": 630,
      "loc": {
        "start": {
          "line": 20,
          "column": 19
        },
        "end": {
          "line": 20,
          "column": 29
        }
      }
    },
    {
      "type": {
        "label": ";",
        "beforeExpr": true,
        "startsExpr": false,
        "rightAssociative": false,
        "isLoop": false,
        "isAssign": false,
        "prefix": false,
        "postfix": false,
        "binop": null,
        "updateContext": null
      },
      "start": 630,
      "end": 631,
      "loc": {
        "start": {
          "line": 20,
          "column": 29
        },
        "end": {
          "line": 20,
          "column": 30
        }
      }
    },
    {
      "type": {
        "label": "export",
        "keyword": "export",
        "beforeExpr": false,
        "startsExpr": false,
        "rightAssociative": false,
        "isLoop": false,
        "isAssign": false,
        "prefix": false,
        "postfix": false,
        "binop": null,
        "updateContext": null
      },
      "value": "export",
      "start": 632,
      "end": 638,
      "loc": {
        "start": {
          "line": 21,
          "column": 0
        },
        "end": {
          "line": 21,
          "column": 6
        }
      }
    },
    {
      "type": {
        "label": "name",
        "beforeExpr": false,
        "startsExpr": true,
        "rightAssociative": false,
        "isLoop": false,
        "isAssign": false,
        "prefix": false,
        "postfix": false,
        "binop": null
      },
      "value": "comp21",
      "start": 639,
      "end": 645,
      "loc": {
        "start": {
          "line": 21,
          "column": 7
        },
        "end": {
          "line": 21,
          "column": 13
        }
      }
    },
    {
      "type": {
        "label": "name",
        "beforeExpr": false,
        "startsExpr": true,
        "rightAssociative": false,
        "isLoop": false,
        "isAssign": false,
        "prefix": false,
        "postfix": false,
        "binop": null
      },
      "value": "from",
      "start": 646,
      "end": 650,
      "loc": {
        "start": {
          "line": 21,
          "column": 14
        },
        "end": {
          "line": 21,
          "column": 18
        }
      }
    },
    {
      "type": {
        "label": "string",
        "beforeExpr": false,
        "startsExpr": true,
        "rightAssociative": false,
        "isLoop": false,
        "isAssign": false,
        "prefix": false,
        "postfix": false,
        "binop": null,
        "updateContext": null
      },
      "value": "./comp21",
      "start": 651,
      "end": 661,
      "loc": {
        "start": {
          "line": 21,
          "column": 19
        },
        "end": {
          "line": 21,
          "column": 29
        }
      }
    },
    {
      "type": {
        "label": ";",
        "beforeExpr": true,
        "startsExpr": false,
        "rightAssociative": false,
        "isLoop": false,
        "isAssign": false,
        "prefix": false,
        "postfix": false,
        "binop": null,
        "updateContext": null
      },
      "start": 661,
      "end": 662,
      "loc": {
        "start": {
          "line": 21,
          "column": 29
        },
        "end": {
          "line": 21,
          "column": 30
        }
      }
    },
    {
      "type": {
        "label": "eof",
        "beforeExpr": false,
        "startsExpr": false,
        "rightAssociative": false,
        "isLoop": false,
        "isAssign": false,
        "prefix": false,
        "postfix": false,
        "binop": null,
        "updateContext": null
      },
      "start": 663,
      "end": 663,
      "loc": {
        "start": {
          "line": 22,
          "column": 0
        },
        "end": {
          "line": 22,
          "column": 0
        }
      }
    }
  ]
}