{
  "type": "File",
  "start": 0,
  "end": 396,
  "loc": {
    "start": {
      "line": 1,
      "column": 0
    },
    "end": {
      "line": 20,
      "column": 0
    }
  },
  "program": {
    "type": "Program",
    "start": 0,
    "end": 396,
    "loc": {
      "start": {
        "line": 1,
        "column": 0
      },
      "end": {
        "line": 20,
        "column": 0
      }
    },
    "sourceType": "module",
    "body": [
      {
        "type": "ExportDefaultDeclaration",
        "start": 0,
        "end": 394,
        "loc": {
          "start": {
            "line": 1,
            "column": 0
          },
          "end": {
            "line": 19,
            "column": 2
          }
        },
        "declaration": {
          "type": "ObjectExpression",
          "start": 15,
          "end": 393,
          "loc": {
            "start": {
              "line": 1,
              "column": 15
            },
            "end": {
              "line": 19,
              "column": 1
            }
          },
          "properties": [
            {
              "type": "ObjectProperty",
              "start": 20,
              "end": 44,
              "loc": {
                "start": {
                  "line": 2,
                  "column": 2
                },
                "end": {
                  "line": 2,
                  "column": 26
                }
              },
              "method": false,
              "shorthand": false,
              "computed": false,
              "key": {
                "type": "StringLiteral",
                "start": 20,
                "end": 26,
                "loc": {
                  "start": {
                    "line": 2,
                    "column": 2
                  },
                  "end": {
                    "line": 2,
                    "column": 8
                  }
                },
                "extra": {
                  "rawValue": "type",
                  "raw": "'type'"
                },
                "value": "type"
              },
              "value": {
                "type": "StringLiteral",
                "start": 28,
                "end": 44,
                "loc": {
                  "start": {
                    "line": 2,
                    "column": 10
                  },
                  "end": {
                    "line": 2,
                    "column": 26
                  }
                },
                "extra": {
                  "rawValue": "stripeCheckout",
                  "raw": "'stripeCheckout'"
                },
                "value": "stripeCheckout"
              }
            },
            {
              "type": "ObjectProperty",
              "start": 49,
              "end": 67,
              "loc": {
                "start": {
                  "line": 3,
                  "column": 2
                },
                "end": {
                  "line": 3,
                  "column": 20
                }
              },
              "method": false,
              "shorthand": false,
              "computed": false,
              "key": {
                "type": "StringLiteral",
                "start": 49,
                "end": 56,
                "loc": {
                  "start": {
                    "line": 3,
                    "column": 2
                  },
                  "end": {
                    "line": 3,
                    "column": 9
                  }
                },
                "extra": {
                  "rawValue": "theme",
                  "raw": "'theme'"
                },
                "value": "theme"
              },
              "value": {
                "type": "StringLiteral",
                "start": 58,
                "end": 67,
                "loc": {
                  "start": {
                    "line": 3,
                    "column": 11
                  },
                  "end": {
                    "line": 3,
                    "column": 20
                  }
                },
                "extra": {
                  "rawValue": "primary",
                  "raw": "'primary'"
                },
                "value": "primary"
              }
            },
            {
              "type": "ObjectProperty",
              "start": 72,
              "end": 97,
              "loc": {
                "start": {
                  "line": 4,
                  "column": 2
                },
                "end": {
                  "line": 4,
                  "column": 27
                }
              },
              "method": false,
              "shorthand": false,
              "computed": false,
              "key": {
                "type": "StringLiteral",
                "start": 72,
                "end": 90,
                "loc": {
                  "start": {
                    "line": 4,
                    "column": 2
                  },
                  "end": {
                    "line": 4,
                    "column": 20
                  }
                },
                "extra": {
                  "rawValue": "disableOnInvalid",
                  "raw": "'disableOnInvalid'"
                },
                "value": "disableOnInvalid"
              },
              "value": {
                "type": "BooleanLiteral",
                "start": 92,
                "end": 97,
                "loc": {
                  "start": {
                    "line": 4,
                    "column": 22
                  },
                  "end": {
                    "line": 4,
                    "column": 27
                  }
                },
                "value": false
              }
            },
            {
              "type": "ObjectProperty",
              "start": 102,
              "end": 120,
              "loc": {
                "start": {
                  "line": 5,
                  "column": 2
                },
                "end": {
                  "line": 5,
                  "column": 20
                }
              },
              "method": false,
              "shorthand": false,
              "computed": false,
              "key": {
                "type": "StringLiteral",
                "start": 102,
                "end": 110,
                "loc": {
                  "start": {
                    "line": 5,
                    "column": 2
                  },
                  "end": {
                    "line": 5,
                    "column": 10
                  }
                },
                "extra": {
                  "rawValue": "action",
                  "raw": "'action'"
                },
                "value": "action"
              },
              "value": {
                "type": "StringLiteral",
                "start": 112,
                "end": 120,
                "loc": {
                  "start": {
                    "line": 5,
                    "column": 12
                  },
                  "end": {
                    "line": 5,
                    "column": 20
                  }
                },
                "extra": {
                  "rawValue": "button",
                  "raw": "'button'"
                },
                "value": "button"
              }
            },
            {
              "type": "ObjectProperty",
              "start": 125,
              "end": 139,
              "loc": {
                "start": {
                  "line": 6,
                  "column": 2
                },
                "end": {
                  "line": 6,
                  "column": 16
                }
              },
              "method": false,
              "shorthand": false,
              "computed": false,
              "key": {
                "type": "StringLiteral",
                "start": 125,
                "end": 132,
                "loc": {
                  "start": {
                    "line": 6,
                    "column": 2
                  },
                  "end": {
                    "line": 6,
                    "column": 9
                  }
                },
                "extra": {
                  "rawValue": "block",
                  "raw": "'block'"
                },
                "value": "block"
              },
              "value": {
                "type": "BooleanLiteral",
                "start": 134,
                "end": 139,
                "loc": {
                  "start": {
                    "line": 6,
                    "column": 11
                  },
                  "end": {
                    "line": 6,
                    "column": 16
                  }
                },
                "value": false
              }
            },
            {
              "type": "ObjectProperty",
              "start": 144,
              "end": 159,
              "loc": {
                "start": {
                  "line": 7,
                  "column": 2
                },
                "end": {
                  "line": 7,
                  "column": 17
                }
              },
              "method": false,
              "shorthand": false,
              "computed": false,
              "key": {
                "type": "StringLiteral",
                "start": 144,
                "end": 155,
                "loc": {
                  "start": {
                    "line": 7,
                    "column": 2
                  },
                  "end": {
                    "line": 7,
                    "column": 13
                  }
                },
                "extra": {
                  "rawValue": "rightIcon",
                  "raw": "'rightIcon'"
                },
                "value": "rightIcon"
              },
              "value": {
                "type": "StringLiteral",
                "start": 157,
                "end": 159,
                "loc": {
                  "start": {
                    "line": 7,
                    "column": 15
                  },
                  "end": {
                    "line": 7,
                    "column": 17
                  }
                },
                "extra": {
                  "rawValue": "",
                  "raw": "''"
                },
                "value": ""
              }
            },
            {
              "type": "ObjectProperty",
              "start": 164,
              "end": 178,
              "loc": {
                "start": {
                  "line": 8,
                  "column": 2
                },
                "end": {
                  "line": 8,
                  "column": 16
                }
              },
              "method": false,
              "shorthand": false,
              "computed": false,
              "key": {
                "type": "StringLiteral",
                "start": 164,
                "end": 174,
                "loc": {
                  "start": {
                    "line": 8,
                    "column": 2
                  },
                  "end": {
                    "line": 8,
                    "column": 12
                  }
                },
                "extra": {
                  "rawValue": "leftIcon",
                  "raw": "'leftIcon'"
                },
                "value": "leftIcon"
              },
              "value": {
                "type": "StringLiteral",
                "start": 176,
                "end": 178,
                "loc": {
                  "start": {
                    "line": 8,
                    "column": 14
                  },
                  "end": {
                    "line": 8,
                    "column": 16
                  }
                },
                "extra": {
                  "rawValue": "",
                  "raw": "''"
                },
                "value": ""
              }
            },
            {
              "type": "ObjectProperty",
              "start": 183,
              "end": 195,
              "loc": {
                "start": {
                  "line": 9,
                  "column": 2
                },
                "end": {
                  "line": 9,
                  "column": 14
                }
              },
              "method": false,
              "shorthand": false,
              "computed": false,
              "key": {
                "type": "StringLiteral",
                "start": 183,
                "end": 189,
                "loc": {
                  "start": {
                    "line": 9,
                    "column": 2
                  },
                  "end": {
                    "line": 9,
                    "column": 8
                  }
                },
                "extra": {
                  "rawValue": "size",
                  "raw": "'size'"
                },
                "value": "size"
              },
              "value": {
                "type": "StringLiteral",
                "start": 191,
                "end": 195,
                "loc": {
                  "start": {
                    "line": 9,
                    "column": 10
                  },
                  "end": {
                    "line": 9,
                    "column": 14
                  }
                },
                "extra": {
                  "rawValue": "md",
                  "raw": "'md'"
                },
                "value": "md"
              }
            },
            {
              "type": "ObjectProperty",
              "start": 200,
              "end": 213,
              "loc": {
                "start": {
                  "line": 10,
                  "column": 2
                },
                "end": {
                  "line": 10,
                  "column": 15
                }
              },
              "method": false,
              "shorthand": false,
              "computed": false,
              "key": {
                "type": "StringLiteral",
                "start": 200,
                "end": 205,
                "loc": {
                  "start": {
                    "line": 10,
                    "column": 2
                  },
                  "end": {
                    "line": 10,
                    "column": 7
                  }
                },
                "extra": {
                  "rawValue": "key",
                  "raw": "'key'"
                },
                "value": "key"
              },
              "value": {
                "type": "StringLiteral",
                "start": 207,
                "end": 213,
                "loc": {
                  "start": {
                    "line": 10,
                    "column": 9
                  },
                  "end": {
                    "line": 10,
                    "column": 15
                  }
                },
                "extra": {
                  "rawValue": "card",
                  "raw": "'card'"
                },
                "value": "card"
              }
            },
            {
              "type": "ObjectProperty",
              "start": 218,
              "end": 236,
              "loc": {
                "start": {
                  "line": 11,
                  "column": 2
                },
                "end": {
                  "line": 11,
                  "column": 20
                }
              },
              "method": false,
              "shorthand": false,
              "computed": false,
              "key": {
                "type": "StringLiteral",
                "start": 218,
                "end": 229,
                "loc": {
                  "start": {
                    "line": 11,
                    "column": 2
                  },
                  "end": {
                    "line": 11,
                    "column": 13
                  }
                },
                "extra": {
                  "rawValue": "tableView",
                  "raw": "'tableView'"
                },
                "value": "tableView"
              },
              "value": {
                "type": "BooleanLiteral",
                "start": 231,
                "end": 236,
                "loc": {
                  "start": {
                    "line": 11,
                    "column": 15
                  },
                  "end": {
                    "line": 11,
                    "column": 20
                  }
                },
                "value": false
              }
            },
            {
              "type": "ObjectProperty",
              "start": 241,
              "end": 269,
              "loc": {
                "start": {
                  "line": 12,
                  "column": 2
                },
                "end": {
                  "line": 12,
                  "column": 30
                }
              },
              "method": false,
              "shorthand": false,
              "computed": false,
              "key": {
                "type": "StringLiteral",
                "start": 241,
                "end": 248,
                "loc": {
                  "start": {
                    "line": 12,
                    "column": 2
                  },
                  "end": {
                    "line": 12,
                    "column": 9
                  }
                },
                "extra": {
                  "rawValue": "label",
                  "raw": "'label'"
                },
                "value": "label"
              },
              "value": {
                "type": "StringLiteral",
                "start": 250,
                "end": 269,
                "loc": {
                  "start": {
                    "line": 12,
                    "column": 11
                  },
                  "end": {
                    "line": 12,
                    "column": 30
                  }
                },
                "extra": {
                  "rawValue": "Authorize payment",
                  "raw": "'Authorize payment'"
                },
                "value": "Authorize payment"
              }
            },
            {
              "type": "ObjectProperty",
              "start": 274,
              "end": 287,
              "loc": {
                "start": {
                  "line": 13,
                  "column": 2
                },
                "end": {
                  "line": 13,
                  "column": 15
                }
              },
              "method": false,
              "shorthand": false,
              "computed": false,
              "key": {
                "type": "StringLiteral",
                "start": 274,
                "end": 281,
                "loc": {
                  "start": {
                    "line": 13,
                    "column": 2
                  },
                  "end": {
                    "line": 13,
                    "column": 9
                  }
                },
                "extra": {
                  "rawValue": "input",
                  "raw": "'input'"
                },
                "value": "input"
              },
              "value": {
                "type": "BooleanLiteral",
                "start": 283,
                "end": 287,
                "loc": {
                  "start": {
                    "line": 13,
                    "column": 11
                  },
                  "end": {
                    "line": 13,
                    "column": 15
                  }
                },
                "value": true
              }
            },
            {
              "type": "ObjectProperty",
              "start": 292,
              "end": 390,
              "loc": {
                "start": {
                  "line": 14,
                  "column": 2
                },
                "end": {
                  "line": 18,
                  "column": 3
                }
              },
              "method": false,
              "shorthand": false,
              "computed": false,
              "key": {
                "type": "StringLiteral",
                "start": 292,
                "end": 300,
                "loc": {
                  "start": {
                    "line": 14,
                    "column": 2
                  },
                  "end": {
                    "line": 14,
                    "column": 10
                  }
                },
                "extra": {
                  "rawValue": "stripe",
                  "raw": "'stripe'"
                },
                "value": "stripe"
              },
              "value": {
                "type": "ObjectExpression",
                "start": 302,
                "end": 390,
                "loc": {
                  "start": {
                    "line": 14,
                    "column": 12
                  },
                  "end": {
                    "line": 18,
                    "column": 3
                  }
                },
                "properties": [
                  {
                    "type": "ObjectProperty",
                    "start": 309,
                    "end": 321,
                    "loc": {
                      "start": {
                        "line": 15,
                        "column": 4
                      },
                      "end": {
                        "line": 15,
                        "column": 16
                      }
                    },
                    "method": false,
                    "shorthand": false,
                    "computed": false,
                    "key": {
                      "type": "StringLiteral",
                      "start": 309,
                      "end": 317,
                      "loc": {
                        "start": {
                          "line": 15,
                          "column": 4
                        },
                        "end": {
                          "line": 15,
                          "column": 12
                        }
                      },
                      "extra": {
                        "rawValue": "apiKey",
                        "raw": "'apiKey'"
                      },
                      "value": "apiKey"
                    },
                    "value": {
                      "type": "StringLiteral",
                      "start": 319,
                      "end": 321,
                      "loc": {
                        "start": {
                          "line": 15,
                          "column": 14
                        },
                        "end": {
                          "line": 15,
                          "column": 16
                        }
                      },
                      "extra": {
                        "rawValue": "",
                        "raw": "''"
                      },
                      "value": ""
                    }
                  },
                  {
                    "type": "ObjectProperty",
                    "start": 328,
                    "end": 354,
                    "loc": {
                      "start": {
                        "line": 16,
                        "column": 4
                      },
                      "end": {
                        "line": 16,
                        "column": 30
                      }
                    },
                    "method": false,
                    "shorthand": false,
                    "computed": false,
                    "key": {
                      "type": "StringLiteral",
                      "start": 328,
                      "end": 350,
                      "loc": {
                        "start": {
                          "line": 16,
                          "column": 4
                        },
                        "end": {
                          "line": 16,
                          "column": 26
                        }
                      },
                      "extra": {
                        "rawValue": "handlerConfiguration",
                        "raw": "'handlerConfiguration'"
                      },
                      "value": "handlerConfiguration"
                    },
                    "value": {
                      "type": "ObjectExpression",
                      "start": 352,
                      "end": 354,
                      "loc": {
                        "start": {
                          "line": 16,
                          "column": 28
                        },
                        "end": {
                          "line": 16,
                          "column": 30
                        }
                      },
                      "properties": []
                    }
                  },
                  {
                    "type": "ObjectProperty",
                    "start": 361,
                    "end": 385,
                    "loc": {
                      "start": {
                        "line": 17,
                        "column": 4
                      },
                      "end": {
                        "line": 17,
                        "column": 28
                      }
                    },
                    "method": false,
                    "shorthand": false,
                    "computed": false,
                    "key": {
                      "type": "StringLiteral",
                      "start": 361,
                      "end": 381,
                      "loc": {
                        "start": {
                          "line": 17,
                          "column": 4
                        },
                        "end": {
                          "line": 17,
                          "column": 24
                        }
                      },
                      "extra": {
                        "rawValue": "popupConfiguration",
                        "raw": "'popupConfiguration'"
                      },
                      "value": "popupConfiguration"
                    },
                    "value": {
                      "type": "ObjectExpression",
                      "start": 383,
                      "end": 385,
                      "loc": {
                        "start": {
                          "line": 17,
                          "column": 26
                        },
                        "end": {
                          "line": 17,
                          "column": 28
                        }
                      },
                      "properties": []
                    }
                  }
                ]
              }
            }
          ],
          "leadingComments": [],
          "trailingComments": []
        }
      }
    ],
    "directives": []
  },
  "comments": [],
  "tokens": [
    {
      "type": {
        "label": "export",
        "keyword": "export",
        "beforeExpr": false,
        "startsExpr": false,
        "rightAssociative": false,
        "isLoop": false,
        "isAssign": false,
        "prefix": false,
        "postfix": false,
        "binop": null,
        "updateContext": null
      },
      "value": "export",
      "start": 0,
      "end": 6,
      "loc": {
        "start": {
          "line": 1,
          "column": 0
        },
        "end": {
          "line": 1,
          "column": 6
        }
      }
    },
    {
      "type": {
        "label": "default",
        "keyword": "default",
        "beforeExpr": true,
        "startsExpr": false,
        "rightAssociative": false,
        "isLoop": false,
        "isAssign": false,
        "prefix": false,
        "postfix": false,
        "binop": null,
        "updateContext": null
      },
      "value": "default",
      "start": 7,
      "end": 14,
      "loc": {
        "start": {
          "line": 1,
          "column": 7
        },
        "end": {
          "line": 1,
          "column": 14
        }
      }
    },
    {
      "type": {
        "label": "{",
        "beforeExpr": true,
        "startsExpr": true,
        "rightAssociative": false,
        "isLoop": false,
        "isAssign": false,
        "prefix": false,
        "postfix": false,
        "binop": null
      },
      "start": 15,
      "end": 16,
      "loc": {
        "start": {
          "line": 1,
          "column": 15
        },
        "end": {
          "line": 1,
          "column": 16
        }
      }
    },
    {
      "type": {
        "label": "string",
        "beforeExpr": false,
        "startsExpr": true,
        "rightAssociative": false,
        "isLoop": false,
        "isAssign": false,
        "prefix": false,
        "postfix": false,
        "binop": null,
        "updateContext": null
      },
      "value": "type",
      "start": 20,
      "end": 26,
      "loc": {
        "start": {
          "line": 2,
          "column": 2
        },
        "end": {
          "line": 2,
          "column": 8
        }
      }
    },
    {
      "type": {
        "label": ":",
        "beforeExpr": true,
        "startsExpr": false,
        "rightAssociative": false,
        "isLoop": false,
        "isAssign": false,
        "prefix": false,
        "postfix": false,
        "binop": null,
        "updateContext": null
      },
      "start": 26,
      "end": 27,
      "loc": {
        "start": {
          "line": 2,
          "column": 8
        },
        "end": {
          "line": 2,
          "column": 9
        }
      }
    },
    {
      "type": {
        "label": "string",
        "beforeExpr": false,
        "startsExpr": true,
        "rightAssociative": false,
        "isLoop": false,
        "isAssign": false,
        "prefix": false,
        "postfix": false,
        "binop": null,
        "updateContext": null
      },
      "value": "stripeCheckout",
      "start": 28,
      "end": 44,
      "loc": {
        "start": {
          "line": 2,
          "column": 10
        },
        "end": {
          "line": 2,
          "column": 26
        }
      }
    },
    {
      "type": {
        "label": ",",
        "beforeExpr": true,
        "startsExpr": false,
        "rightAssociative": false,
        "isLoop": false,
        "isAssign": false,
        "prefix": false,
        "postfix": false,
        "binop": null,
        "updateContext": null
      },
      "start": 44,
      "end": 45,
      "loc": {
        "start": {
          "line": 2,
          "column": 26
        },
        "end": {
          "line": 2,
          "column": 27
        }
      }
    },
    {
      "type": {
        "label": "string",
        "beforeExpr": false,
        "startsExpr": true,
        "rightAssociative": false,
        "isLoop": false,
        "isAssign": false,
        "prefix": false,
        "postfix": false,
        "binop": null,
        "updateContext": null
      },
      "value": "theme",
      "start": 49,
      "end": 56,
      "loc": {
        "start": {
          "line": 3,
          "column": 2
        },
        "end": {
          "line": 3,
          "column": 9
        }
      }
    },
    {
      "type": {
        "label": ":",
        "beforeExpr": true,
        "startsExpr": false,
        "rightAssociative": false,
        "isLoop": false,
        "isAssign": false,
        "prefix": false,
        "postfix": false,
        "binop": null,
        "updateContext": null
      },
      "start": 56,
      "end": 57,
      "loc": {
        "start": {
          "line": 3,
          "column": 9
        },
        "end": {
          "line": 3,
          "column": 10
        }
      }
    },
    {
      "type": {
        "label": "string",
        "beforeExpr": false,
        "startsExpr": true,
        "rightAssociative": false,
        "isLoop": false,
        "isAssign": false,
        "prefix": false,
        "postfix": false,
        "binop": null,
        "updateContext": null
      },
      "value": "primary",
      "start": 58,
      "end": 67,
      "loc": {
        "start": {
          "line": 3,
          "column": 11
        },
        "end": {
          "line": 3,
          "column": 20
        }
      }
    },
    {
      "type": {
        "label": ",",
        "beforeExpr": true,
        "startsExpr": false,
        "rightAssociative": false,
        "isLoop": false,
        "isAssign": false,
        "prefix": false,
        "postfix": false,
        "binop": null,
        "updateContext": null
      },
      "start": 67,
      "end": 68,
      "loc": {
        "start": {
          "line": 3,
          "column": 20
        },
        "end": {
          "line": 3,
          "column": 21
        }
      }
    },
    {
      "type": {
        "label": "string",
        "beforeExpr": false,
        "startsExpr": true,
        "rightAssociative": false,
        "isLoop": false,
        "isAssign": false,
        "prefix": false,
        "postfix": false,
        "binop": null,
        "updateContext": null
      },
      "value": "disableOnInvalid",
      "start": 72,
      "end": 90,
      "loc": {
        "start": {
          "line": 4,
          "column": 2
        },
        "end": {
          "line": 4,
          "column": 20
        }
      }
    },
    {
      "type": {
        "label": ":",
        "beforeExpr": true,
        "startsExpr": false,
        "rightAssociative": false,
        "isLoop": false,
        "isAssign": false,
        "prefix": false,
        "postfix": false,
        "binop": null,
        "updateContext": null
      },
      "start": 90,
      "end": 91,
      "loc": {
        "start": {
          "line": 4,
          "column": 20
        },
        "end": {
          "line": 4,
          "column": 21
        }
      }
    },
    {
      "type": {
        "label": "false",
        "keyword": "false",
        "beforeExpr": false,
        "startsExpr": true,
        "rightAssociative": false,
        "isLoop": false,
        "isAssign": false,
        "prefix": false,
        "postfix": false,
        "binop": null,
        "updateContext": null
      },
      "value": "false",
      "start": 92,
      "end": 97,
      "loc": {
        "start": {
          "line": 4,
          "column": 22
        },
        "end": {
          "line": 4,
          "column": 27
        }
      }
    },
    {
      "type": {
        "label": ",",
        "beforeExpr": true,
        "startsExpr": false,
        "rightAssociative": false,
        "isLoop": false,
        "isAssign": false,
        "prefix": false,
        "postfix": false,
        "binop": null,
        "updateContext": null
      },
      "start": 97,
      "end": 98,
      "loc": {
        "start": {
          "line": 4,
          "column": 27
        },
        "end": {
          "line": 4,
          "column": 28
        }
      }
    },
    {
      "type": {
        "label": "string",
        "beforeExpr": false,
        "startsExpr": true,
        "rightAssociative": false,
        "isLoop": false,
        "isAssign": false,
        "prefix": false,
        "postfix": false,
        "binop": null,
        "updateContext": null
      },
      "value": "action",
      "start": 102,
      "end": 110,
      "loc": {
        "start": {
          "line": 5,
          "column": 2
        },
        "end": {
          "line": 5,
          "column": 10
        }
      }
    },
    {
      "type": {
        "label": ":",
        "beforeExpr": true,
        "startsExpr": false,
        "rightAssociative": false,
        "isLoop": false,
        "isAssign": false,
        "prefix": false,
        "postfix": false,
        "binop": null,
        "updateContext": null
      },
      "start": 110,
      "end": 111,
      "loc": {
        "start": {
          "line": 5,
          "column": 10
        },
        "end": {
          "line": 5,
          "column": 11
        }
      }
    },
    {
      "type": {
        "label": "string",
        "beforeExpr": false,
        "startsExpr": true,
        "rightAssociative": false,
        "isLoop": false,
        "isAssign": false,
        "prefix": false,
        "postfix": false,
        "binop": null,
        "updateContext": null
      },
      "value": "button",
      "start": 112,
      "end": 120,
      "loc": {
        "start": {
          "line": 5,
          "column": 12
        },
        "end": {
          "line": 5,
          "column": 20
        }
      }
    },
    {
      "type": {
        "label": ",",
        "beforeExpr": true,
        "startsExpr": false,
        "rightAssociative": false,
        "isLoop": false,
        "isAssign": false,
        "prefix": false,
        "postfix": false,
        "binop": null,
        "updateContext": null
      },
      "start": 120,
      "end": 121,
      "loc": {
        "start": {
          "line": 5,
          "column": 20
        },
        "end": {
          "line": 5,
          "column": 21
        }
      }
    },
    {
      "type": {
        "label": "string",
        "beforeExpr": false,
        "startsExpr": true,
        "rightAssociative": false,
        "isLoop": false,
        "isAssign": false,
        "prefix": false,
        "postfix": false,
        "binop": null,
        "updateContext": null
      },
      "value": "block",
      "start": 125,
      "end": 132,
      "loc": {
        "start": {
          "line": 6,
          "column": 2
        },
        "end": {
          "line": 6,
          "column": 9
        }
      }
    },
    {
      "type": {
        "label": ":",
        "beforeExpr": true,
        "startsExpr": false,
        "rightAssociative": false,
        "isLoop": false,
        "isAssign": false,
        "prefix": false,
        "postfix": false,
        "binop": null,
        "updateContext": null
      },
      "start": 132,
      "end": 133,
      "loc": {
        "start": {
          "line": 6,
          "column": 9
        },
        "end": {
          "line": 6,
          "column": 10
        }
      }
    },
    {
      "type": {
        "label": "false",
        "keyword": "false",
        "beforeExpr": false,
        "startsExpr": true,
        "rightAssociative": false,
        "isLoop": false,
        "isAssign": false,
        "prefix": false,
        "postfix": false,
        "binop": null,
        "updateContext": null
      },
      "value": "false",
      "start": 134,
      "end": 139,
      "loc": {
        "start": {
          "line": 6,
          "column": 11
        },
        "end": {
          "line": 6,
          "column": 16
        }
      }
    },
    {
      "type": {
        "label": ",",
        "beforeExpr": true,
        "startsExpr": false,
        "rightAssociative": false,
        "isLoop": false,
        "isAssign": false,
        "prefix": false,
        "postfix": false,
        "binop": null,
        "updateContext": null
      },
      "start": 139,
      "end": 140,
      "loc": {
        "start": {
          "line": 6,
          "column": 16
        },
        "end": {
          "line": 6,
          "column": 17
        }
      }
    },
    {
      "type": {
        "label": "string",
        "beforeExpr": false,
        "startsExpr": true,
        "rightAssociative": false,
        "isLoop": false,
        "isAssign": false,
        "prefix": false,
        "postfix": false,
        "binop": null,
        "updateContext": null
      },
      "value": "rightIcon",
      "start": 144,
      "end": 155,
      "loc": {
        "start": {
          "line": 7,
          "column": 2
        },
        "end": {
          "line": 7,
          "column": 13
        }
      }
    },
    {
      "type": {
        "label": ":",
        "beforeExpr": true,
        "startsExpr": false,
        "rightAssociative": false,
        "isLoop": false,
        "isAssign": false,
        "prefix": false,
        "postfix": false,
        "binop": null,
        "updateContext": null
      },
      "start": 155,
      "end": 156,
      "loc": {
        "start": {
          "line": 7,
          "column": 13
        },
        "end": {
          "line": 7,
          "column": 14
        }
      }
    },
    {
      "type": {
        "label": "string",
        "beforeExpr": false,
        "startsExpr": true,
        "rightAssociative": false,
        "isLoop": false,
        "isAssign": false,
        "prefix": false,
        "postfix": false,
        "binop": null,
        "updateContext": null
      },
      "value": "",
      "start": 157,
      "end": 159,
      "loc": {
        "start": {
          "line": 7,
          "column": 15
        },
        "end": {
          "line": 7,
          "column": 17
        }
      }
    },
    {
      "type": {
        "label": ",",
        "beforeExpr": true,
        "startsExpr": false,
        "rightAssociative": false,
        "isLoop": false,
        "isAssign": false,
        "prefix": false,
        "postfix": false,
        "binop": null,
        "updateContext": null
      },
      "start": 159,
      "end": 160,
      "loc": {
        "start": {
          "line": 7,
          "column": 17
        },
        "end": {
          "line": 7,
          "column": 18
        }
      }
    },
    {
      "type": {
        "label": "string",
        "beforeExpr": false,
        "startsExpr": true,
        "rightAssociative": false,
        "isLoop": false,
        "isAssign": false,
        "prefix": false,
        "postfix": false,
        "binop": null,
        "updateContext": null
      },
      "value": "leftIcon",
      "start": 164,
      "end": 174,
      "loc": {
        "start": {
          "line": 8,
          "column": 2
        },
        "end": {
          "line": 8,
          "column": 12
        }
      }
    },
    {
      "type": {
        "label": ":",
        "beforeExpr": true,
        "startsExpr": false,
        "rightAssociative": false,
        "isLoop": false,
        "isAssign": false,
        "prefix": false,
        "postfix": false,
        "binop": null,
        "updateContext": null
      },
      "start": 174,
      "end": 175,
      "loc": {
        "start": {
          "line": 8,
          "column": 12
        },
        "end": {
          "line": 8,
          "column": 13
        }
      }
    },
    {
      "type": {
        "label": "string",
        "beforeExpr": false,
        "startsExpr": true,
        "rightAssociative": false,
        "isLoop": false,
        "isAssign": false,
        "prefix": false,
        "postfix": false,
        "binop": null,
        "updateContext": null
      },
      "value": "",
      "start": 176,
      "end": 178,
      "loc": {
        "start": {
          "line": 8,
          "column": 14
        },
        "end": {
          "line": 8,
          "column": 16
        }
      }
    },
    {
      "type": {
        "label": ",",
        "beforeExpr": true,
        "startsExpr": false,
        "rightAssociative": false,
        "isLoop": false,
        "isAssign": false,
        "prefix": false,
        "postfix": false,
        "binop": null,
        "updateContext": null
      },
      "start": 178,
      "end": 179,
      "loc": {
        "start": {
          "line": 8,
          "column": 16
        },
        "end": {
          "line": 8,
          "column": 17
        }
      }
    },
    {
      "type": {
        "label": "string",
        "beforeExpr": false,
        "startsExpr": true,
        "rightAssociative": false,
        "isLoop": false,
        "isAssign": false,
        "prefix": false,
        "postfix": false,
        "binop": null,
        "updateContext": null
      },
      "value": "size",
      "start": 183,
      "end": 189,
      "loc": {
        "start": {
          "line": 9,
          "column": 2
        },
        "end": {
          "line": 9,
          "column": 8
        }
      }
    },
    {
      "type": {
        "label": ":",
        "beforeExpr": true,
        "startsExpr": false,
        "rightAssociative": false,
        "isLoop": false,
        "isAssign": false,
        "prefix": false,
        "postfix": false,
        "binop": null,
        "updateContext": null
      },
      "start": 189,
      "end": 190,
      "loc": {
        "start": {
          "line": 9,
          "column": 8
        },
        "end": {
          "line": 9,
          "column": 9
        }
      }
    },
    {
      "type": {
        "label": "string",
        "beforeExpr": false,
        "startsExpr": true,
        "rightAssociative": false,
        "isLoop": false,
        "isAssign": false,
        "prefix": false,
        "postfix": false,
        "binop": null,
        "updateContext": null
      },
      "value": "md",
      "start": 191,
      "end": 195,
      "loc": {
        "start": {
          "line": 9,
          "column": 10
        },
        "end": {
          "line": 9,
          "column": 14
        }
      }
    },
    {
      "type": {
        "label": ",",
        "beforeExpr": true,
        "startsExpr": false,
        "rightAssociative": false,
        "isLoop": false,
        "isAssign": false,
        "prefix": false,
        "postfix": false,
        "binop": null,
        "updateContext": null
      },
      "start": 195,
      "end": 196,
      "loc": {
        "start": {
          "line": 9,
          "column": 14
        },
        "end": {
          "line": 9,
          "column": 15
        }
      }
    },
    {
      "type": {
        "label": "string",
        "beforeExpr": false,
        "startsExpr": true,
        "rightAssociative": false,
        "isLoop": false,
        "isAssign": false,
        "prefix": false,
        "postfix": false,
        "binop": null,
        "updateContext": null
      },
      "value": "key",
      "start": 200,
      "end": 205,
      "loc": {
        "start": {
          "line": 10,
          "column": 2
        },
        "end": {
          "line": 10,
          "column": 7
        }
      }
    },
    {
      "type": {
        "label": ":",
        "beforeExpr": true,
        "startsExpr": false,
        "rightAssociative": false,
        "isLoop": false,
        "isAssign": false,
        "prefix": false,
        "postfix": false,
        "binop": null,
        "updateContext": null
      },
      "start": 205,
      "end": 206,
      "loc": {
        "start": {
          "line": 10,
          "column": 7
        },
        "end": {
          "line": 10,
          "column": 8
        }
      }
    },
    {
      "type": {
        "label": "string",
        "beforeExpr": false,
        "startsExpr": true,
        "rightAssociative": false,
        "isLoop": false,
        "isAssign": false,
        "prefix": false,
        "postfix": false,
        "binop": null,
        "updateContext": null
      },
      "value": "card",
      "start": 207,
      "end": 213,
      "loc": {
        "start": {
          "line": 10,
          "column": 9
        },
        "end": {
          "line": 10,
          "column": 15
        }
      }
    },
    {
      "type": {
        "label": ",",
        "beforeExpr": true,
        "startsExpr": false,
        "rightAssociative": false,
        "isLoop": false,
        "isAssign": false,
        "prefix": false,
        "postfix": false,
        "binop": null,
        "updateContext": null
      },
      "start": 213,
      "end": 214,
      "loc": {
        "start": {
          "line": 10,
          "column": 15
        },
        "end": {
          "line": 10,
          "column": 16
        }
      }
    },
    {
      "type": {
        "label": "string",
        "beforeExpr": false,
        "startsExpr": true,
        "rightAssociative": false,
        "isLoop": false,
        "isAssign": false,
        "prefix": false,
        "postfix": false,
        "binop": null,
        "updateContext": null
      },
      "value": "tableView",
      "start": 218,
      "end": 229,
      "loc": {
        "start": {
          "line": 11,
          "column": 2
        },
        "end": {
          "line": 11,
          "column": 13
        }
      }
    },
    {
      "type": {
        "label": ":",
        "beforeExpr": true,
        "startsExpr": false,
        "rightAssociative": false,
        "isLoop": false,
        "isAssign": false,
        "prefix": false,
        "postfix": false,
        "binop": null,
        "updateContext": null
      },
      "start": 229,
      "end": 230,
      "loc": {
        "start": {
          "line": 11,
          "column": 13
        },
        "end": {
          "line": 11,
          "column": 14
        }
      }
    },
    {
      "type": {
        "label": "false",
        "keyword": "false",
        "beforeExpr": false,
        "startsExpr": true,
        "rightAssociative": false,
        "isLoop": false,
        "isAssign": false,
        "prefix": false,
        "postfix": false,
        "binop": null,
        "updateContext": null
      },
      "value": "false",
      "start": 231,
      "end": 236,
      "loc": {
        "start": {
          "line": 11,
          "column": 15
        },
        "end": {
          "line": 11,
          "column": 20
        }
      }
    },
    {
      "type": {
        "label": ",",
        "beforeExpr": true,
        "startsExpr": false,
        "rightAssociative": false,
        "isLoop": false,
        "isAssign": false,
        "prefix": false,
        "postfix": false,
        "binop": null,
        "updateContext": null
      },
      "start": 236,
      "end": 237,
      "loc": {
        "start": {
          "line": 11,
          "column": 20
        },
        "end": {
          "line": 11,
          "column": 21
        }
      }
    },
    {
      "type": {
        "label": "string",
        "beforeExpr": false,
        "startsExpr": true,
        "rightAssociative": false,
        "isLoop": false,
        "isAssign": false,
        "prefix": false,
        "postfix": false,
        "binop": null,
        "updateContext": null
      },
      "value": "label",
      "start": 241,
      "end": 248,
      "loc": {
        "start": {
          "line": 12,
          "column": 2
        },
        "end": {
          "line": 12,
          "column": 9
        }
      }
    },
    {
      "type": {
        "label": ":",
        "beforeExpr": true,
        "startsExpr": false,
        "rightAssociative": false,
        "isLoop": false,
        "isAssign": false,
        "prefix": false,
        "postfix": false,
        "binop": null,
        "updateContext": null
      },
      "start": 248,
      "end": 249,
      "loc": {
        "start": {
          "line": 12,
          "column": 9
        },
        "end": {
          "line": 12,
          "column": 10
        }
      }
    },
    {
      "type": {
        "label": "string",
        "beforeExpr": false,
        "startsExpr": true,
        "rightAssociative": false,
        "isLoop": false,
        "isAssign": false,
        "prefix": false,
        "postfix": false,
        "binop": null,
        "updateContext": null
      },
      "value": "Authorize payment",
      "start": 250,
      "end": 269,
      "loc": {
        "start": {
          "line": 12,
          "column": 11
        },
        "end": {
          "line": 12,
          "column": 30
        }
      }
    },
    {
      "type": {
        "label": ",",
        "beforeExpr": true,
        "startsExpr": false,
        "rightAssociative": false,
        "isLoop": false,
        "isAssign": false,
        "prefix": false,
        "postfix": false,
        "binop": null,
        "updateContext": null
      },
      "start": 269,
      "end": 270,
      "loc": {
        "start": {
          "line": 12,
          "column": 30
        },
        "end": {
          "line": 12,
          "column": 31
        }
      }
    },
    {
      "type": {
        "label": "string",
        "beforeExpr": false,
        "startsExpr": true,
        "rightAssociative": false,
        "isLoop": false,
        "isAssign": false,
        "prefix": false,
        "postfix": false,
        "binop": null,
        "updateContext": null
      },
      "value": "input",
      "start": 274,
      "end": 281,
      "loc": {
        "start": {
          "line": 13,
          "column": 2
        },
        "end": {
          "line": 13,
          "column": 9
        }
      }
    },
    {
      "type": {
        "label": ":",
        "beforeExpr": true,
        "startsExpr": false,
        "rightAssociative": false,
        "isLoop": false,
        "isAssign": false,
        "prefix": false,
        "postfix": false,
        "binop": null,
        "updateContext": null
      },
      "start": 281,
      "end": 282,
      "loc": {
        "start": {
          "line": 13,
          "column": 9
        },
        "end": {
          "line": 13,
          "column": 10
        }
      }
    },
    {
      "type": {
        "label": "true",
        "keyword": "true",
        "beforeExpr": false,
        "startsExpr": true,
        "rightAssociative": false,
        "isLoop": false,
        "isAssign": false,
        "prefix": false,
        "postfix": false,
        "binop": null,
        "updateContext": null
      },
      "value": "true",
      "start": 283,
      "end": 287,
      "loc": {
        "start": {
          "line": 13,
          "column": 11
        },
        "end": {
          "line": 13,
          "column": 15
        }
      }
    },
    {
      "type": {
        "label": ",",
        "beforeExpr": true,
        "startsExpr": false,
        "rightAssociative": false,
        "isLoop": false,
        "isAssign": false,
        "prefix": false,
        "postfix": false,
        "binop": null,
        "updateContext": null
      },
      "start": 287,
      "end": 288,
      "loc": {
        "start": {
          "line": 13,
          "column": 15
        },
        "end": {
          "line": 13,
          "column": 16
        }
      }
    },
    {
      "type": {
        "label": "string",
        "beforeExpr": false,
        "startsExpr": true,
        "rightAssociative": false,
        "isLoop": false,
        "isAssign": false,
        "prefix": false,
        "postfix": false,
        "binop": null,
        "updateContext": null
      },
      "value": "stripe",
      "start": 292,
      "end": 300,
      "loc": {
        "start": {
          "line": 14,
          "column": 2
        },
        "end": {
          "line": 14,
          "column": 10
        }
      }
    },
    {
      "type": {
        "label": ":",
        "beforeExpr": true,
        "startsExpr": false,
        "rightAssociative": false,
        "isLoop": false,
        "isAssign": false,
        "prefix": false,
        "postfix": false,
        "binop": null,
        "updateContext": null
      },
      "start": 300,
      "end": 301,
      "loc": {
        "start": {
          "line": 14,
          "column": 10
        },
        "end": {
          "line": 14,
          "column": 11
        }
      }
    },
    {
      "type": {
        "label": "{",
        "beforeExpr": true,
        "startsExpr": true,
        "rightAssociative": false,
        "isLoop": false,
        "isAssign": false,
        "prefix": false,
        "postfix": false,
        "binop": null
      },
      "start": 302,
      "end": 303,
      "loc": {
        "start": {
          "line": 14,
          "column": 12
        },
        "end": {
          "line": 14,
          "column": 13
        }
      }
    },
    {
      "type": {
        "label": "string",
        "beforeExpr": false,
        "startsExpr": true,
        "rightAssociative": false,
        "isLoop": false,
        "isAssign": false,
        "prefix": false,
        "postfix": false,
        "binop": null,
        "updateContext": null
      },
      "value": "apiKey",
      "start": 309,
      "end": 317,
      "loc": {
        "start": {
          "line": 15,
          "column": 4
        },
        "end": {
          "line": 15,
          "column": 12
        }
      }
    },
    {
      "type": {
        "label": ":",
        "beforeExpr": true,
        "startsExpr": false,
        "rightAssociative": false,
        "isLoop": false,
        "isAssign": false,
        "prefix": false,
        "postfix": false,
        "binop": null,
        "updateContext": null
      },
      "start": 317,
      "end": 318,
      "loc": {
        "start": {
          "line": 15,
          "column": 12
        },
        "end": {
          "line": 15,
          "column": 13
        }
      }
    },
    {
      "type": {
        "label": "string",
        "beforeExpr": false,
        "startsExpr": true,
        "rightAssociative": false,
        "isLoop": false,
        "isAssign": false,
        "prefix": false,
        "postfix": false,
        "binop": null,
        "updateContext": null
      },
      "value": "",
      "start": 319,
      "end": 321,
      "loc": {
        "start": {
          "line": 15,
          "column": 14
        },
        "end": {
          "line": 15,
          "column": 16
        }
      }
    },
    {
      "type": {
        "label": ",",
        "beforeExpr": true,
        "startsExpr": false,
        "rightAssociative": false,
        "isLoop": false,
        "isAssign": false,
        "prefix": false,
        "postfix": false,
        "binop": null,
        "updateContext": null
      },
      "start": 321,
      "end": 322,
      "loc": {
        "start": {
          "line": 15,
          "column": 16
        },
        "end": {
          "line": 15,
          "column": 17
        }
      }
    },
    {
      "type": {
        "label": "string",
        "beforeExpr": false,
        "startsExpr": true,
        "rightAssociative": false,
        "isLoop": false,
        "isAssign": false,
        "prefix": false,
        "postfix": false,
        "binop": null,
        "updateContext": null
      },
      "value": "handlerConfiguration",
      "start": 328,
      "end": 350,
      "loc": {
        "start": {
          "line": 16,
          "column": 4
        },
        "end": {
          "line": 16,
          "column": 26
        }
      }
    },
    {
      "type": {
        "label": ":",
        "beforeExpr": true,
        "startsExpr": false,
        "rightAssociative": false,
        "isLoop": false,
        "isAssign": false,
        "prefix": false,
        "postfix": false,
        "binop": null,
        "updateContext": null
      },
      "start": 350,
      "end": 351,
      "loc": {
        "start": {
          "line": 16,
          "column": 26
        },
        "end": {
          "line": 16,
          "column": 27
        }
      }
    },
    {
      "type": {
        "label": "{",
        "beforeExpr": true,
        "startsExpr": true,
        "rightAssociative": false,
        "isLoop": false,
        "isAssign": false,
        "prefix": false,
        "postfix": false,
        "binop": null
      },
      "start": 352,
      "end": 353,
      "loc": {
        "start": {
          "line": 16,
          "column": 28
        },
        "end": {
          "line": 16,
          "column": 29
        }
      }
    },
    {
      "type": {
        "label": "}",
        "beforeExpr": false,
        "startsExpr": false,
        "rightAssociative": false,
        "isLoop": false,
        "isAssign": false,
        "prefix": false,
        "postfix": false,
        "binop": null
      },
      "start": 353,
      "end": 354,
      "loc": {
        "start": {
          "line": 16,
          "column": 29
        },
        "end": {
          "line": 16,
          "column": 30
        }
      }
    },
    {
      "type": {
        "label": ",",
        "beforeExpr": true,
        "startsExpr": false,
        "rightAssociative": false,
        "isLoop": false,
        "isAssign": false,
        "prefix": false,
        "postfix": false,
        "binop": null,
        "updateContext": null
      },
      "start": 354,
      "end": 355,
      "loc": {
        "start": {
          "line": 16,
          "column": 30
        },
        "end": {
          "line": 16,
          "column": 31
        }
      }
    },
    {
      "type": {
        "label": "string",
        "beforeExpr": false,
        "startsExpr": true,
        "rightAssociative": false,
        "isLoop": false,
        "isAssign": false,
        "prefix": false,
        "postfix": false,
        "binop": null,
        "updateContext": null
      },
      "value": "popupConfiguration",
      "start": 361,
      "end": 381,
      "loc": {
        "start": {
          "line": 17,
          "column": 4
        },
        "end": {
          "line": 17,
          "column": 24
        }
      }
    },
    {
      "type": {
        "label": ":",
        "beforeExpr": true,
        "startsExpr": false,
        "rightAssociative": false,
        "isLoop": false,
        "isAssign": false,
        "prefix": false,
        "postfix": false,
        "binop": null,
        "updateContext": null
      },
      "start": 381,
      "end": 382,
      "loc": {
        "start": {
          "line": 17,
          "column": 24
        },
        "end": {
          "line": 17,
          "column": 25
        }
      }
    },
    {
      "type": {
        "label": "{",
        "beforeExpr": true,
        "startsExpr": true,
        "rightAssociative": false,
        "isLoop": false,
        "isAssign": false,
        "prefix": false,
        "postfix": false,
        "binop": null
      },
      "start": 383,
      "end": 384,
      "loc": {
        "start": {
          "line": 17,
          "column": 26
        },
        "end": {
          "line": 17,
          "column": 27
        }
      }
    },
    {
      "type": {
        "label": "}",
        "beforeExpr": false,
        "startsExpr": false,
        "rightAssociative": false,
        "isLoop": false,
        "isAssign": false,
        "prefix": false,
        "postfix": false,
        "binop": null
      },
      "start": 384,
      "end": 385,
      "loc": {
        "start": {
          "line": 17,
          "column": 27
        },
        "end": {
          "line": 17,
          "column": 28
        }
      }
    },
    {
      "type": {
        "label": "}",
        "beforeExpr": false,
        "startsExpr": false,
        "rightAssociative": false,
        "isLoop": false,
        "isAssign": false,
        "prefix": false,
        "postfix": false,
        "binop": null
      },
      "start": 389,
      "end": 390,
      "loc": {
        "start": {
          "line": 18,
          "column": 2
        },
        "end": {
          "line": 18,
          "column": 3
        }
      }
    },
    {
      "type": {
        "label": "}",
        "beforeExpr": false,
        "startsExpr": false,
        "rightAssociative": false,
        "isLoop": false,
        "isAssign": false,
        "prefix": false,
        "postfix": false,
        "binop": null
      },
      "start": 392,
      "end": 393,
      "loc": {
        "start": {
          "line": 19,
          "column": 0
        },
        "end": {
          "line": 19,
          "column": 1
        }
      }
    },
    {
      "type": {
        "label": ";",
        "beforeExpr": true,
        "startsExpr": false,
        "rightAssociative": false,
        "isLoop": false,
        "isAssign": false,
        "prefix": false,
        "postfix": false,
        "binop": null,
        "updateContext": null
      },
      "start": 393,
      "end": 394,
      "loc": {
        "start": {
          "line": 19,
          "column": 1
        },
        "end": {
          "line": 19,
          "column": 2
        }
      }
    },
    {
      "type": {
        "label": "eof",
        "beforeExpr": false,
        "startsExpr": false,
        "rightAssociative": false,
        "isLoop": false,
        "isAssign": false,
        "prefix": false,
        "postfix": false,
        "binop": null,
        "updateContext": null
      },
      "start": 396,
      "end": 396,
      "loc": {
        "start": {
          "line": 20,
          "column": 0
        },
        "end": {
          "line": 20,
          "column": 0
        }
      }
    }
  ]
}